Workbook

Sheet BROADER CATEGORIES
A1: Sector | B1: Year | C1: Month | D1: Cereals and products | E1: Meat and fish | F1: Egg | G1: Milk and products | H1: Oils and fats | I1: Fruits | J1: Vegetables | K1: Pulses and products | L1: Sugar and Confectionery | M1: Spices | N1: Non-alcoholic beverages | O1: Prepared meals, snacks, sweets etc. | P1: Food and beverages | Q1: Pan, tobacco and intoxicants | R1: Clothing | S1: Footwear | T1: Clothing and footwear | U1: Housing | V1: Fuel and light | W1: Household goods and services | X1: Health | Y1: Transport and communication | Z1: Recreation and amusement | AA1: Education | AB1: Personal care and effects | AC1: Miscellaneous | AD1: General index | AE1: Food | AF1: Cloth | AG1: House | AH1: CONTRIBUTION IN HOUSE | AI1: CONTRIBUTION IN CLOTH | AJ1: CONTRIBUTION IN FOOD | AK1: CONTRIBUTION IN MIS_ITEM | AL1: CONTRIBUTION IN PER_CARE_ITEM | AM1: CONTRIBUTION IN EDUCATION | AN1: CONTRIBUTION IN REC_AND_AMU | AO1: CONTRIBUTION IN TR_COM | AP1: CONTRIBUTION IN HEALTH | AQ1: CONTRIBUTION IN L&F | AR1: MONTH IN NUM | AS1: CONCAT Y&M | AT1: ESSENTIAL SERVICES | AU1: TOTAL BROADER CATEGORIES
A2: Rural | B2: 2023 | C2: May | D2: 173.2 | E2: 211.5 | F2: 171 | G2: 179.6 | H2: 173.3 | I2: 169 | J2: 148.7 | K2: 174.9 | L2: 121.9 | M2: 213.04 | N2: 178.7 | O2: 191.1 | P2: 176.8 | Q2: 199.9 | R2: 191.2 | S2: 185.35 | T2: 190.8 | U2: 140.85 | V2: 182.5 | W2: 179.8 | X2: 187.8 | Y2: 169.7 | Z2: 173.8 | AA2: 180.3 | AB2: 184.9 | AC2: 179.5 | AD2: 179.8 | AE2: 177.9 | AF2: 189.96667 | AG2: 160.325 | AH2: =All_India_Index_Upto_April23__1[[#This Row],[House]]/All_India_Index_Upto_April23__1[[#This Row],[TOTAL BROADER CATEGORIES]] -> 0.089732886 | AI2: =All_India_Index_Upto_April23__1[[#This Row],[Cloth]]/All_India_Index_Upto_April23__1[[#This Row],[TOTAL BROADER CATEGORIES]] -> 0.10632314 | AJ2: =All_India_Index_Upto_April23__1[[#This Row],[Food]]/All_India_Index_Upto_April23__1[[#This Row],[TOTAL BROADER CATEGORIES]] -> 0.099569502 | AK2: =All_India_Index_Upto_April23__1[[#This Row],[Miscellaneous]]/All_India_Index_Upto_April23__1[[#This Row],[TOTAL BROADER CATEGORIES]] -> 0.10046501 | AL2: =All_India_Index_Upto_April23__1[[#This Row],[Personal care and effects]]/All_India_Index_Upto_April23__1[[#This Row],[TOTAL BROADER CATEGORIES]] -> 0.10348736 | AM2: =All_India_Index_Upto_April23__1[[#This Row],[Education]]/All_India_Index_Upto_April23__1[[#This Row],[TOTAL BROADER CATEGORIES]] -> 0.10091277 | AN2: =All_India_Index_Upto_April23__1[[#This Row],[Recreation and amusement]]/All_India_Index_Upto_April23__1[[#This Row],[TOTAL BROADER CATEGORIES]] -> 0.097274758 | AO2: =All_India_Index_Upto_April23__1[[#This Row],[Transport and communication]]/All_India_Index_Upto_April23__1[[#This Row],[TOTAL BROADER CATEGORIES]] -> 0.094980014 | AP2: =All_India_Index_Upto_April23__1[[#This Row],[Health]]/All_India_Index_Upto_April23__1[[#This Row],[TOTAL BROADER CATEGORIES]] -> 0.10511047 | AQ2: =All_India_Index_Upto_April23__1[[#This Row],[Fuel and light]]/All_India_Index_Upto_April23__1[[#This Row],[TOTAL BROADER CATEGORIES]] -> 0.10214409 | AR2: =MONTH(1 & All_India_Index_Upto_April23__1[[#This Row],[Month]]) -> 5 | AS2: =All_India_Index_Upto_April23__1[[#This Row],[MONTH IN NUM]]&"/"&All_India_Index_Upto_April23__1[[#This Row],[Year]] -> 5/2023 | AT2: =SUM((All_India_Index_Upto_April23__1[[#This Row],[Education]]+All_India_Index_Upto_April23__1[[#This Row],[Household goods and services]]+All_India_Index_Upto_April23__1[[#This Row],[Fuel and light]]+All_India_Index_Upto_April23__1[[#This Row],[Housing]]+All_India_Index_Upto_April23__1[[#This Row],[Clothing and footwear]]+All_India_Index_Upto_April23__1[[#This Row],[Footwear]]+All_India_Index_Upto_April23__1[[#This Row],[Clothing]])/7) -> 178.68571 | AU2: =(All_India_Index_Upto_April23__1[[#This Row],[House]]+All_India_Index_Upto_April23__1[[#This Row],[Cloth]]+All_India_Index_Upto_April23__1[[#This Row],[Food]]+All_India_Index_Upto_April23__1[[#This Row],[Miscellaneous]]+All_India_Index_Upto_April23__1[[#This Row],[Personal care and effects]]+All_India_Index_Upto_April23__1[[#This Row],[Education]]+All_India_Index_Upto_April23__1[[#This Row],[Recreation and amusement]]+All_India_Index_Upto_April23__1[[#This Row],[Transport and communication]]+All_India_Index_Upto_April23__1[[#This Row],[Health]]+All_India_Index_Upto_April23__1[[#This Row],[Fuel and light]]) -> 1786.6917
A3: Urban | B3: 2023 | C3: May | D3: 174.7 | E3: 219.4 | F3: 176.7 | G3: 179.4 | H3: 164.4 | I3: 175.8 | J3: 185 | K3: 176.9 | L3: 124.2 | M3: 211.9 | N3: 165.9 | O3: 197.7 | P3: 183.1 | Q3: 204.2 | R3: 181.3 | S3: 168.1 | T3: 179.3 | U3: 175.6 | V3: 183.4 | W3: 170.1 | X3: 182.2 | Y3: 160.4 | Z3: 169.2 | AA3: 174.8 | AB3: 185.6 | AC3: 171.6 | AD3: 178.2 | AE3: 181.37857 | AF3: 176.23333 | AG3: 172.85 | AH3: =All_India_Index_Upto_April23__1[[#This Row],[House]]/All_India_Index_Upto_April23__1[[#This Row],[TOTAL BROADER CATEGORIES]] -> 0.098340869 | AI3: =All_India_Index_Upto_April23__1[[#This Row],[Cloth]]/All_India_Index_Upto_April23__1[[#This Row],[TOTAL BROADER CATEGORIES]] -> 0.10026578 | AJ3: =All_India_Index_Upto_April23__1[[#This Row],[Food]]/All_India_Index_Upto_April23__1[[#This Row],[TOTAL BROADER CATEGORIES]] -> 0.10319309 | AK3: =All_India_Index_Upto_April23__1[[#This Row],[Miscellaneous]]/All_India_Index_Upto_April23__1[[#This Row],[TOTAL BROADER CATEGORIES]] -> 0.097629697 | AL3: =All_India_Index_Upto_April23__1[[#This Row],[Personal care and effects]]/All_India_Index_Upto_April23__1[[#This Row],[TOTAL BROADER CATEGORIES]] -> 0.10559482 | AM3: =All_India_Index_Upto_April23__1[[#This Row],[Education]]/All_India_Index_Upto_April23__1[[#This Row],[TOTAL BROADER CATEGORIES]] -> 0.099450298 | AN3: =All_India_Index_Upto_April23__1[[#This Row],[Recreation and amusement]]/All_India_Index_Upto_April23__1[[#This Row],[TOTAL BROADER CATEGORIES]] -> 0.096264247 | AO3: =All_India_Index_Upto_April23__1[[#This Row],[Transport and communication]]/All_India_Index_Upto_April23__1[[#This Row],[TOTAL BROADER CATEGORIES]] -> 0.091257596 | AP3: =All_India_Index_Upto_April23__1[[#This Row],[Health]]/All_India_Index_Upto_April23__1[[#This Row],[TOTAL BROADER CATEGORIES]] -> 0.10366044 | AQ3: =All_India_Index_Upto_April23__1[[#This Row],[Fuel and light]]/All_India_Index_Upto_April23__1[[#This Row],[TOTAL BROADER CATEGORIES]] -> 0.10434316 | AR3: =MONTH(1 & All_India_Index_Upto_April23__1[[#This Row],[Month]]) -> 5 | AS3: =All_India_Index_Upto_April23__1[[#This Row],[MONTH IN NUM]]&"/"&All_India_Index_Upto_April23__1[[#This Row],[Year]] -> 5/2023 | AT3: =SUM((All_India_Index_Upto_April23__1[[#This Row],[Education]]+All_India_Index_Upto_April23__1[[#This Row],[Household goods and services]]+All_India_Index_Upto_April23__1[[#This Row],[Fuel and light]]+All_India_Index_Upto_April23__1[[#This Row],[Housing]]+All_India_Index_Upto_April23__1[[#This Row],[Clothing and footwear]]+All_India_Index_Upto_April23__1[[#This Row],[Footwear]]+All_India_Index_Upto_April23__1[[#This Row],[Clothing]])/7) -> 176.08571 | AU3: =(All_India_Index_Upto_April23__1[[#This Row],[House]]+All_India_Index_Upto_April23__1[[#This Row],[Cloth]]+All_India_Index_Upto_April23__1[[#This Row],[Food]]+All_India_Index_Upto_April23__1[[#This Row],[Miscellaneous]]+All_India_Index_Upto_April23__1[[#This Row],[Personal care and effects]]+All_India_Index_Upto_April23__1[[#This Row],[Education]]+All_India_Index_Upto_April23__1[[#This Row],[Recreation and amusement]]+All_India_Index_Upto_April23__1[[#This Row],[Transport and communication]]+All_India_Index_Upto_April23__1[[#This Row],[Health]]+All_India_Index_Upto_April23__1[[#This Row],[Fuel and light]]) -> 1757.6619
A4: Rural+Urban | B4: 2022 | C4: May | D4: 154.1 | E4: 217 | F4: 162.4 | G4: 164.9 | H4: 189.675 | I4: 171 | J4: 174.9 | K4: 164.7 | L4: 119.7 | M4: 184.9 | N4: 167.1 | O4: 182.5 | P4: 173.3 | Q4: 194.1 | R4: 175.6 | S4: 168.4 | T4: 174.6 | U4: 167.5 | V4: 174.6 | W4: 165.2 | X4: 174.8 | Y4: 163 | Z4: 165.1 | AA4: 167.9 | AB4: 168.4 | AC4: 167.5 | AD4: 171.7 | AE4: 173.78571 | AF4: 172.86667 | AG4: 166.35 | AH4: =All_India_Index_Upto_April23__1[[#This Row],[House]]/All_India_Index_Upto_April23__1[[#This Row],[TOTAL BROADER CATEGORIES]] -> 0.098182002 | AI4: =All_India_Index_Upto_April23__1[[#This Row],[Cloth]]/All_India_Index_Upto_April23__1[[#This Row],[TOTAL BROADER CATEGORIES]] -> 0.10202823 | AJ4: =All_India_Index_Upto_April23__1[[#This Row],[Food]]/All_India_Index_Upto_April23__1[[#This Row],[TOTAL BROADER CATEGORIES]] -> 0.10257066 | AK4: =All_India_Index_Upto_April23__1[[#This Row],[Miscellaneous]]/All_India_Index_Upto_April23__1[[#This Row],[TOTAL BROADER CATEGORIES]] -> 0.098860748 | AL4: =All_India_Index_Upto_April23__1[[#This Row],[Personal care and effects]]/All_India_Index_Upto_April23__1[[#This Row],[TOTAL BROADER CATEGORIES]] -> 0.09939194 | AM4: =All_India_Index_Upto_April23__1[[#This Row],[Education]]/All_India_Index_Upto_April23__1[[#This Row],[TOTAL BROADER CATEGORIES]] -> 0.099096833 | AN4: =All_India_Index_Upto_April23__1[[#This Row],[Recreation and amusement]]/All_India_Index_Upto_April23__1[[#This Row],[TOTAL BROADER CATEGORIES]] -> 0.097444235 | AO4: =All_India_Index_Upto_April23__1[[#This Row],[Transport and communication]]/All_India_Index_Upto_April23__1[[#This Row],[TOTAL BROADER CATEGORIES]] -> 0.096204787 | AP4: =All_India_Index_Upto_April23__1[[#This Row],[Health]]/All_India_Index_Upto_April23__1[[#This Row],[TOTAL BROADER CATEGORIES]] -> 0.10316931 | AQ4: =All_India_Index_Upto_April23__1[[#This Row],[Fuel and light]]/All_India_Index_Upto_April23__1[[#This Row],[TOTAL BROADER CATEGORIES]] -> 0.10305126 | AR4: =MONTH(1 & All_India_Index_Upto_April23__1[[#This Row],[Month]]) -> 5 | AS4: =All_India_Index_Upto_April23__1[[#This Row],[MONTH IN NUM]]&"/"&All_India_Index_Upto_April23__1[[#This Row],[Year]] -> 5/2022 | AT4: =SUM((All_India_Index_Upto_April23__1[[#This Row],[Education]]+All_India_Index_Upto_April23__1[[#This Row],[Household goods and services]]+All_India_Index_Upto_April23__1[[#This Row],[Fuel and light]]+All_India_Index_Upto_April23__1[[#This Row],[Housing]]+All_India_Index_Upto_April23__1[[#This Row],[Clothing and footwear]]+All_India_Index_Upto_April23__1[[#This Row],[Footwear]]+All_India_Index_Upto_April23__1[[#This Row],[Clothing]])/7) -> 170.54286 | AU4: =(All_India_Index_Upto_April23__1[[#This Row],[House]]+All_India_Index_Upto_April23__1[[#This Row],[Cloth]]+All_India_Index_Upto_April23__1[[#This Row],[Food]]+All_India_Index_Upto_April23__1[[#This Row],[Miscellaneous]]+All_India_Index_Upto_April23__1[[#This Row],[Personal care and effects]]+All_India_Index_Upto_April23__1[[#This Row],[Education]]+All_India_Index_Upto_April23__1[[#This Row],[Recreation and amusement]]+All_India_Index_Upto_April23__1[[#This Row],[Transport and communication]]+All_India_Index_Upto_April23__1[[#This Row],[Health]]+All_India_Index_Upto_April23__1[[#This Row],[Fuel and light]]) -> 1694.3024
A5: Rural+Urban | B5: 2022 | C5: June | D5: 155 | E5: 219.4 | F5: 170.8 | G5: 165.8 | H5: 189.675 | I5: 169.7 | J5: 182.3 | K5: 164.3 | L5: 119.9 | M5: 187.1 | N5: 167.9 | O5: 183.9 | P5: 174.9 | Q5: 194.3 | R5: 177.1 | S5: 169.9 | T5: 176 | U5: 166.8 | V5: 176 | W5: 166.4 | X5: 175.4 | Y5: 161.1 | Z5: 165.8 | AA5: 169 | AB5: 169.4 | AC5: 167.5 | AD5: 172.6 | AE5: 175.44286 | AF5: 174.33333 | AG5: 166.6 | AH5: =All_India_Index_Upto_April23__1[[#This Row],[House]]/All_India_Index_Upto_April23__1[[#This Row],[TOTAL BROADER CATEGORIES]] -> 0.097966796 | AI5: =All_India_Index_Upto_April23__1[[#This Row],[Cloth]]/All_India_Index_Upto_April23__1[[#This Row],[TOTAL BROADER CATEGORIES]] -> 0.10251427 | AJ5: =All_India_Index_Upto_April23__1[[#This Row],[Food]]/All_India_Index_Upto_April23__1[[#This Row],[TOTAL BROADER CATEGORIES]] -> 0.10316671 | AK5: =All_India_Index_Upto_April23__1[[#This Row],[Miscellaneous]]/All_India_Index_Upto_April23__1[[#This Row],[TOTAL BROADER CATEGORIES]] -> 0.098496028 | AL5: =All_India_Index_Upto_April23__1[[#This Row],[Personal care and effects]]/All_India_Index_Upto_April23__1[[#This Row],[TOTAL BROADER CATEGORIES]] -> 0.099613296 | AM5: =All_India_Index_Upto_April23__1[[#This Row],[Education]]/All_India_Index_Upto_April23__1[[#This Row],[TOTAL BROADER CATEGORIES]] -> 0.099378082 | AN5: =All_India_Index_Upto_April23__1[[#This Row],[Recreation and amusement]]/All_India_Index_Upto_April23__1[[#This Row],[TOTAL BROADER CATEGORIES]] -> 0.097496367 | AO5: =All_India_Index_Upto_April23__1[[#This Row],[Transport and communication]]/All_India_Index_Upto_April23__1[[#This Row],[TOTAL BROADER CATEGORIES]] -> 0.094732598 | AP5: =All_India_Index_Upto_April23__1[[#This Row],[Health]]/All_India_Index_Upto_April23__1[[#This Row],[TOTAL BROADER CATEGORIES]] -> 0.10314151 | AQ5: =All_India_Index_Upto_April23__1[[#This Row],[Fuel and light]]/All_India_Index_Upto_April23__1[[#This Row],[TOTAL BROADER CATEGORIES]] -> 0.10349433 | AR5: =MONTH(1 & All_India_Index_Upto_April23__1[[#This Row],[Month]]) -> 6 | AS5: =All_India_Index_Upto_April23__1[[#This Row],[MONTH IN NUM]]&"/"&All_India_Index_Upto_April23__1[[#This Row],[Year]] -> 6/2022 | AT5: =SUM((All_India_Index_Upto_April23__1[[#This Row],[Education]]+All_India_Index_Upto_April23__1[[#This Row],[Household goods and services]]+All_India_Index_Upto_April23__1[[#This Row],[Fuel and light]]+All_India_Index_Upto_April23__1[[#This Row],[Housing]]+All_India_Index_Upto_April23__1[[#This Row],[Clothing and footwear]]+All_India_Index_Upto_April23__1[[#This Row],[Footwear]]+All_India_Index_Upto_April23__1[[#This Row],[Clothing]])/7) -> 171.6 | AU5: =(All_India_Index_Upto_April23__1[[#This Row],[House]]+All_India_Index_Upto_April23__1[[#This Row],[Cloth]]+All_India_Index_Upto_April23__1[[#This Row],[Food]]+All_India_Index_Upto_April23__1[[#This Row],[Miscellaneous]]+All_India_Index_Upto_April23__1[[#This Row],[Personal care and effects]]+All_India_Index_Upto_April23__1[[#This Row],[Education]]+All_India_Index_Upto_April23__1[[#This Row],[Recreation and amusement]]+All_India_Index_Upto_April23__1[[#This Row],[Transport and communication]]+All_India_Index_Upto_April23__1[[#This Row],[Health]]+All_India_Index_Upto_April23__1[[#This Row],[Fuel and light]]) -> 1700.5762
A6: Rural | B6: 2023 | C6: April | D6: 173.3 | E6: 206.9 | F6: 167.9 | G6: 178.2 | H6: 178.5 | I6: 173.7 | J6: 142.8 | K6: 172.8 | L6: 120.4 | M6: 213.04 | N6: 178.2 | O6: 190.5 | P6: 175.5 | Q6: 199.5 | R6: 190.7 | S6: 185.35 | T6: 190.2 | U6: 140.85 | V6: 181.5 | W6: 179.1 | X6: 187.2 | Y6: 169.4 | Z6: 173.2 | AA6: 179.4 | AB6: 183.8 | AC6: 178.9 | AD6: 178.8 | AE6: 176.69286 | AF6: 189.4 | AG6: 159.975 | AH6: =All_India_Index_Upto_April23__1[[#This Row],[House]]/All_India_Index_Upto_April23__1[[#This Row],[TOTAL BROADER CATEGORIES]] -> 0.089900472 | AI6: =All_India_Index_Upto_April23__1[[#This Row],[Cloth]]/All_India_Index_Upto_April23__1[[#This Row],[TOTAL BROADER CATEGORIES]] -> 0.10643631 | AJ6: =All_India_Index_Upto_April23__1[[#This Row],[Food]]/All_India_Index_Upto_April23__1[[#This Row],[TOTAL BROADER CATEGORIES]] -> 0.099295335 | AK6: =All_India_Index_Upto_April23__1[[#This Row],[Miscellaneous]]/All_India_Index_Upto_April23__1[[#This Row],[TOTAL BROADER CATEGORIES]] -> 0.10053567 | AL6: =All_India_Index_Upto_April23__1[[#This Row],[Personal care and effects]]/All_India_Index_Upto_April23__1[[#This Row],[TOTAL BROADER CATEGORIES]] -> 0.10328931 | AM6: =All_India_Index_Upto_April23__1[[#This Row],[Education]]/All_India_Index_Upto_April23__1[[#This Row],[TOTAL BROADER CATEGORIES]] -> 0.10081666 | AN6: =All_India_Index_Upto_April23__1[[#This Row],[Recreation and amusement]]/All_India_Index_Upto_April23__1[[#This Row],[TOTAL BROADER CATEGORIES]] -> 0.097332469 | AO6: =All_India_Index_Upto_April23__1[[#This Row],[Transport and communication]]/All_India_Index_Upto_April23__1[[#This Row],[TOTAL BROADER CATEGORIES]] -> 0.095196999 | AP6: =All_India_Index_Upto_April23__1[[#This Row],[Health]]/All_India_Index_Upto_April23__1[[#This Row],[TOTAL BROADER CATEGORIES]] -> 0.10519999 | AQ6: =All_India_Index_Upto_April23__1[[#This Row],[Fuel and light]]/All_India_Index_Upto_April23__1[[#This Row],[TOTAL BROADER CATEGORIES]] -> 0.10199678 | AR6: =MONTH(1 & All_India_Index_Upto_April23__1[[#This Row],[Month]]) -> 4 | AS6: =All_India_Index_Upto_April23__1[[#This Row],[MONTH IN NUM]]&"/"&All_India_Index_Upto_April23__1[[#This Row],[Year]] -> 4/2023 | AT6: =SUM((All_India_Index_Upto_April23__1[[#This Row],[Education]]+All_India_Index_Upto_April23__1[[#This Row],[Household goods and services]]+All_India_Index_Upto_April23__1[[#This Row],[Fuel and light]]+All_India_Index_Upto_April23__1[[#This Row],[Housing]]+All_India_Index_Upto_April23__1[[#This Row],[Clothing and footwear]]+All_India_Index_Upto_April23__1[[#This Row],[Footwear]]+All_India_Index_Upto_April23__1[[#This Row],[Clothing]])/7) -> 178.15714 | AU6: =(All_India_Index_Upto_April23__1[[#This Row],[House]]+All_India_Index_Upto_April23__1[[#This Row],[Cloth]]+All_India_Index_Upto_April23__1[[#This Row],[Food]]+All_India_Index_Upto_April23__1[[#This Row],[Miscellaneous]]+All_India_Index_Upto_April23__1[[#This Row],[Personal care and effects]]+All_India_Index_Upto_April23__1[[#This Row],[Education]]+All_India_Index_Upto_April23__1[[#This Row],[Recreation and amusement]]+All_India_Index_Upto_April23__1[[#This Row],[Transport and communication]]+All_India_Index_Upto_April23__1[[#This Row],[Health]]+All_India_Index_Upto_April23__1[[#This Row],[Fuel and light]]) -> 1779.4679
A7: Urban | B7: 2023 | C7: April | D7: 174.8 | E7: 213.7 | F7: 172.4 | G7: 178.8 | H7: 168.7 | I7: 179.2 | J7: 179.9 | K7: 174.7 | L7: 123.1 | M7: 207.8 | N7: 165.5 | O7: 197 | P7: 182.1 | Q7: 203.5 | R7: 181 | S7: 167.7 | T7: 178.9 | U7: 175.2 | V7: 182.1 | W7: 169.6 | X7: 181.5 | Y7: 160.1 | Z7: 168.8 | AA7: 174.2 | AB7: 184.4 | AC7: 170.9 | AD7: 177.4 | AE7: 180.08571 | AF7: 175.86667 | AG7: 172.4 | AH7: =All_India_Index_Upto_April23__1[[#This Row],[House]]/All_India_Index_Upto_April23__1[[#This Row],[TOTAL BROADER CATEGORIES]] -> 0.098494453 | AI7: =All_India_Index_Upto_April23__1[[#This Row],[Cloth]]/All_India_Index_Upto_April23__1[[#This Row],[TOTAL BROADER CATEGORIES]] -> 0.10047501 | AJ7: =All_India_Index_Upto_April23__1[[#This Row],[Food]]/All_India_Index_Upto_April23__1[[#This Row],[TOTAL BROADER CATEGORIES]] -> 0.10288541 | AK7: =All_India_Index_Upto_April23__1[[#This Row],[Miscellaneous]]/All_India_Index_Upto_April23__1[[#This Row],[TOTAL BROADER CATEGORIES]] -> 0.097637483 | AL7: =All_India_Index_Upto_April23__1[[#This Row],[Personal care and effects]]/All_India_Index_Upto_April23__1[[#This Row],[TOTAL BROADER CATEGORIES]] -> 0.10535022 | AM7: =All_India_Index_Upto_April23__1[[#This Row],[Education]]/All_India_Index_Upto_April23__1[[#This Row],[TOTAL BROADER CATEGORIES]] -> 0.099522817 | AN7: =All_India_Index_Upto_April23__1[[#This Row],[Recreation and amusement]]/All_India_Index_Upto_April23__1[[#This Row],[TOTAL BROADER CATEGORIES]] -> 0.096437724 | AO7: =All_India_Index_Upto_April23__1[[#This Row],[Transport and communication]]/All_India_Index_Upto_April23__1[[#This Row],[TOTAL BROADER CATEGORIES]] -> 0.091467296 | AP7: =All_India_Index_Upto_April23__1[[#This Row],[Health]]/All_India_Index_Upto_April23__1[[#This Row],[TOTAL BROADER CATEGORIES]] -> 0.10369341 | AQ7: =All_India_Index_Upto_April23__1[[#This Row],[Fuel and light]]/All_India_Index_Upto_April23__1[[#This Row],[TOTAL BROADER CATEGORIES]] -> 0.10403619 | AR7: =MONTH(1 & All_India_Index_Upto_April23__1[[#This Row],[Month]]) -> 4 | AS7: =All_India_Index_Upto_April23__1[[#This Row],[MONTH IN NUM]]&"/"&All_India_Index_Upto_April23__1[[#This Row],[Year]] -> 4/2023 | AT7: =SUM((All_India_Index_Upto_April23__1[[#This Row],[Education]]+All_India_Index_Upto_April23__1[[#This Row],[Household goods and services]]+All_India_Index_Upto_April23__1[[#This Row],[Fuel and light]]+All_India_Index_Upto_April23__1[[#This Row],[Housing]]+All_India_Index_Upto_April23__1[[#This Row],[Clothing and footwear]]+All_India_Index_Upto_April23__1[[#This Row],[Footwear]]+All_India_Index_Upto_April23__1[[#This Row],[Clothing]])/7) -> 175.52857 | AU7: =(All_India_Index_Upto_April23__1[[#This Row],[House]]+All_India_Index_Upto_April23__1[[#This Row],[Cloth]]+All_India_Index_Upto_April23__1[[#This Row],[Food]]+All_India_Index_Upto_April23__1[[#This Row],[Miscellaneous]]+All_India_Index_Upto_April23__1[[#This Row],[Personal care and effects]]+All_India_Index_Upto_April23__1[[#This Row],[Education]]+All_India_Index_Upto_April23__1[[#This Row],[Recreation and amusement]]+All_India_Index_Upto_April23__1[[#This Row],[Transport and communication]]+All_India_Index_Upto_April23__1[[#This Row],[Health]]+All_India_Index_Upto_April23__1[[#This Row],[Fuel and light]]) -> 1750.3524
A8: Rural | B8: 2023 | C8: March | D8: 174.3 | E8: 205.2 | F8: 173.9 | G8: 177 | H8: 183.3 | I8: 167.2 | J8: 140.9 | K8: 170.5 | L8: 119.1 | M8: 212.1 | N8: 177.6 | O8: 189.9 | P8: 174.8 | Q8: 198.4 | R8: 190 | S8: 185.35 | T8: 189.6 | U8: 140.85 | V8: 181.4 | W8: 178.6 | X8: 186.6 | Y8: 169 | Z8: 172.8 | AA8: 178.5 | AB8: 180.7 | AC8: 177.9 | AD8: 178 | AE8: 176.01429 | AF8: 188.86667 | AG8: 159.725 | AH8: =All_India_Index_Upto_April23__1[[#This Row],[House]]/All_India_Index_Upto_April23__1[[#This Row],[TOTAL BROADER CATEGORIES]] -> 0.0901634 | AI8: =All_India_Index_Upto_April23__1[[#This Row],[Cloth]]/All_India_Index_Upto_April23__1[[#This Row],[TOTAL BROADER CATEGORIES]] -> 0.10661362 | AJ8: =All_India_Index_Upto_April23__1[[#This Row],[Food]]/All_India_Index_Upto_April23__1[[#This Row],[TOTAL BROADER CATEGORIES]] -> 0.099358563 | AK8: =All_India_Index_Upto_April23__1[[#This Row],[Miscellaneous]]/All_India_Index_Upto_April23__1[[#This Row],[TOTAL BROADER CATEGORIES]] -> 0.10042303 | AL8: =All_India_Index_Upto_April23__1[[#This Row],[Personal care and effects]]/All_India_Index_Upto_April23__1[[#This Row],[TOTAL BROADER CATEGORIES]] -> 0.10200361 | AM8: =All_India_Index_Upto_April23__1[[#This Row],[Education]]/All_India_Index_Upto_April23__1[[#This Row],[TOTAL BROADER CATEGORIES]] -> 0.10076173 | AN8: =All_India_Index_Upto_April23__1[[#This Row],[Recreation and amusement]]/All_India_Index_Upto_April23__1[[#This Row],[TOTAL BROADER CATEGORIES]] -> 0.097544126 | AO8: =All_India_Index_Upto_April23__1[[#This Row],[Transport and communication]]/All_India_Index_Upto_April23__1[[#This Row],[TOTAL BROADER CATEGORIES]] -> 0.095399059 | AP8: =All_India_Index_Upto_April23__1[[#This Row],[Health]]/All_India_Index_Upto_April23__1[[#This Row],[TOTAL BROADER CATEGORIES]] -> 0.10533411 | AQ8: =All_India_Index_Upto_April23__1[[#This Row],[Fuel and light]]/All_India_Index_Upto_April23__1[[#This Row],[TOTAL BROADER CATEGORIES]] -> 0.10239875 | AR8: =MONTH(1 & All_India_Index_Upto_April23__1[[#This Row],[Month]]) -> 3 | AS8: =All_India_Index_Upto_April23__1[[#This Row],[MONTH IN NUM]]&"/"&All_India_Index_Upto_April23__1[[#This Row],[Year]] -> 3/2023 | AT8: =SUM((All_India_Index_Upto_April23__1[[#This Row],[Education]]+All_India_Index_Upto_April23__1[[#This Row],[Household goods and services]]+All_India_Index_Upto_April23__1[[#This Row],[Fuel and light]]+All_India_Index_Upto_April23__1[[#This Row],[Housing]]+All_India_Index_Upto_April23__1[[#This Row],[Clothing and footwear]]+All_India_Index_Upto_April23__1[[#This Row],[Footwear]]+All_India_Index_Upto_April23__1[[#This Row],[Clothing]])/7) -> 177.75714 | AU8: =(All_India_Index_Upto_April23__1[[#This Row],[House]]+All_India_Index_Upto_April23__1[[#This Row],[Cloth]]+All_India_Index_Upto_April23__1[[#This Row],[Food]]+All_India_Index_Upto_April23__1[[#This Row],[Miscellaneous]]+All_India_Index_Upto_April23__1[[#This Row],[Personal care and effects]]+All_India_Index_Upto_April23__1[[#This Row],[Education]]+All_India_Index_Upto_April23__1[[#This Row],[Recreation and amusement]]+All_India_Index_Upto_April23__1[[#This Row],[Transport and communication]]+All_India_Index_Upto_April23__1[[#This Row],[Health]]+All_India_Index_Upto_April23__1[[#This Row],[Fuel and light]]) -> 1771.506
A9: Urban | B9: 2023 | C9: March | D9: 174.7 | E9: 212.2 | F9: 177.2 | G9: 177.9 | H9: 172.2 | I9: 172.1 | J9: 175.9 | K9: 172.2 | L9: 121.9 | M9: 204.8 | N9: 164.9 | O9: 196.6 | P9: 180.8 | Q9: 202.7 | R9: 180.2 | S9: 167 | T9: 178.2 | U9: 173.5 | V9: 182.6 | W9: 169.2 | X9: 180.8 | Y9: 159.8 | Z9: 168.4 | AA9: 172.5 | AB9: 181.5 | AC9: 170 | AD9: 176.3 | AE9: 179.00714 | AF9: 175.13333 | AG9: 171.35 | AH9: =All_India_Index_Upto_April23__1[[#This Row],[House]]/All_India_Index_Upto_April23__1[[#This Row],[TOTAL BROADER CATEGORIES]] -> 0.098415334 | AI9: =All_India_Index_Upto_April23__1[[#This Row],[Cloth]]/All_India_Index_Upto_April23__1[[#This Row],[TOTAL BROADER CATEGORIES]] -> 0.1005883 | AJ9: =All_India_Index_Upto_April23__1[[#This Row],[Food]]/All_India_Index_Upto_April23__1[[#This Row],[TOTAL BROADER CATEGORIES]] -> 0.10281323 | AK9: =All_India_Index_Upto_April23__1[[#This Row],[Miscellaneous]]/All_India_Index_Upto_April23__1[[#This Row],[TOTAL BROADER CATEGORIES]] -> 0.097639957 | AL9: =All_India_Index_Upto_April23__1[[#This Row],[Personal care and effects]]/All_India_Index_Upto_April23__1[[#This Row],[TOTAL BROADER CATEGORIES]] -> 0.10424501 | AM9: =All_India_Index_Upto_April23__1[[#This Row],[Education]]/All_India_Index_Upto_April23__1[[#This Row],[TOTAL BROADER CATEGORIES]] -> 0.099075839 | AN9: =All_India_Index_Upto_April23__1[[#This Row],[Recreation and amusement]]/All_India_Index_Upto_April23__1[[#This Row],[TOTAL BROADER CATEGORIES]] -> 0.096720993 | AO9: =All_India_Index_Upto_April23__1[[#This Row],[Transport and communication]]/All_India_Index_Upto_April23__1[[#This Row],[TOTAL BROADER CATEGORIES]] -> 0.09178156 | AP9: =All_India_Index_Upto_April23__1[[#This Row],[Health]]/All_India_Index_Upto_April23__1[[#This Row],[TOTAL BROADER CATEGORIES]] -> 0.10384297 | AQ9: =All_India_Index_Upto_April23__1[[#This Row],[Fuel and light]]/All_India_Index_Upto_April23__1[[#This Row],[TOTAL BROADER CATEGORIES]] -> 0.1048768 | AR9: =MONTH(1 & All_India_Index_Upto_April23__1[[#This Row],[Month]]) -> 3 | AS9: =All_India_Index_Upto_April23__1[[#This Row],[MONTH IN NUM]]&"/"&All_India_Index_Upto_April23__1[[#This Row],[Year]] -> 3/2023 | AT9: =SUM((All_India_Index_Upto_April23__1[[#This Row],[Education]]+All_India_Index_Upto_April23__1[[#This Row],[Household goods and services]]+All_India_Index_Upto_April23__1[[#This Row],[Fuel and light]]+All_India_Index_Upto_April23__1[[#This Row],[Housing]]+All_India_Index_Upto_April23__1[[#This Row],[Clothing and footwear]]+All_India_Index_Upto_April23__1[[#This Row],[Footwear]]+All_India_Index_Upto_April23__1[[#This Row],[Clothing]])/7) -> 174.74286 | AU9: =(All_India_Index_Upto_April23__1[[#This Row],[House]]+All_India_Index_Upto_April23__1[[#This Row],[Cloth]]+All_India_Index_Upto_April23__1[[#This Row],[Food]]+All_India_Index_Upto_April23__1[[#This Row],[Miscellaneous]]+All_India_Index_Upto_April23__1[[#This Row],[Personal care and effects]]+All_India_Index_Upto_April23__1[[#This Row],[Education]]+All_India_Index_Upto_April23__1[[#This Row],[Recreation and amusement]]+All_India_Index_Upto_April23__1[[#This Row],[Transport and communication]]+All_India_Index_Upto_April23__1[[#This Row],[Health]]+All_India_Index_Upto_April23__1[[#This Row],[Fuel and light]]) -> 1741.0905
A10: Rural+Urban | B10: 2022 | C10: July | D10: 156.5 | E10: 213 | F10: 175.2 | G10: 166.6 | H10: 189.675 | I10: 174.2 | J10: 182.1 | K10: 164.3 | L10: 120 | M10: 190 | N10: 168.4 | O10: 185.2 | P10: 175 | Q10: 194.6 | R10: 178.3 | S10: 171.3 | T10: 177.3 | U10: 167.8 | V10: 179.6 | W10: 167.4 | X10: 176.1 | Y10: 161.6 | Z10: 166.3 | AA10: 171.4 | AB10: 169.7 | AC10: 168.4 | AD10: 173.4 | AE10: 175.77857 | AF10: 175.63333 | AG10: 167.6 | AH10: =All_India_Index_Upto_April23__1[[#This Row],[House]]/All_India_Index_Upto_April23__1[[#This Row],[TOTAL BROADER CATEGORIES]] -> 0.097890798 | AI10: =All_India_Index_Upto_April23__1[[#This Row],[Cloth]]/All_India_Index_Upto_April23__1[[#This Row],[TOTAL BROADER CATEGORIES]] -> 0.10258286 | AJ10: =All_India_Index_Upto_April23__1[[#This Row],[Food]]/All_India_Index_Upto_April23__1[[#This Row],[TOTAL BROADER CATEGORIES]] -> 0.10266769 | AK10: =All_India_Index_Upto_April23__1[[#This Row],[Miscellaneous]]/All_India_Index_Upto_April23__1[[#This Row],[TOTAL BROADER CATEGORIES]] -> 0.098358057 | AL10: =All_India_Index_Upto_April23__1[[#This Row],[Personal care and effects]]/All_India_Index_Upto_April23__1[[#This Row],[TOTAL BROADER CATEGORIES]] -> 0.099117353 | AM10: =All_India_Index_Upto_April23__1[[#This Row],[Education]]/All_India_Index_Upto_April23__1[[#This Row],[TOTAL BROADER CATEGORIES]] -> 0.10011028 | AN10: =All_India_Index_Upto_April23__1[[#This Row],[Recreation and amusement]]/All_India_Index_Upto_April23__1[[#This Row],[TOTAL BROADER CATEGORIES]] -> 0.097131501 | AO10: =All_India_Index_Upto_April23__1[[#This Row],[Transport and communication]]/All_India_Index_Upto_April23__1[[#This Row],[TOTAL BROADER CATEGORIES]] -> 0.094386354 | AP10: =All_India_Index_Upto_April23__1[[#This Row],[Health]]/All_India_Index_Upto_April23__1[[#This Row],[TOTAL BROADER CATEGORIES]] -> 0.10285543 | AQ10: =All_India_Index_Upto_April23__1[[#This Row],[Fuel and light]]/All_India_Index_Upto_April23__1[[#This Row],[TOTAL BROADER CATEGORIES]] -> 0.10489969 | AR10: =MONTH(1 & All_India_Index_Upto_April23__1[[#This Row],[Month]]) -> 7 | AS10: =All_India_Index_Upto_April23__1[[#This Row],[MONTH IN NUM]]&"/"&All_India_Index_Upto_April23__1[[#This Row],[Year]] -> 7/2022 | AT10: =SUM((All_India_Index_Upto_April23__1[[#This Row],[Education]]+All_India_Index_Upto_April23__1[[#This Row],[Household goods and services]]+All_India_Index_Upto_April23__1[[#This Row],[Fuel and light]]+All_India_Index_Upto_April23__1[[#This Row],[Housing]]+All_India_Index_Upto_April23__1[[#This Row],[Clothing and footwear]]+All_India_Index_Upto_April23__1[[#This Row],[Footwear]]+All_India_Index_Upto_April23__1[[#This Row],[Clothing]])/7) -> 173.3 | AU10: =(All_India_Index_Upto_April23__1[[#This Row],[House]]+All_India_Index_Upto_April23__1[[#This Row],[Cloth]]+All_India_Index_Upto_April23__1[[#This Row],[Food]]+All_India_Index_Upto_April23__1[[#This Row],[Miscellaneous]]+All_India_Index_Upto_April23__1[[#This Row],[Personal care and effects]]+All_India_Index_Upto_April23__1[[#This Row],[Education]]+All_India_Index_Upto_April23__1[[#This Row],[Recreation and amusement]]+All_India_Index_Upto_April23__1[[#This Row],[Transport and communication]]+All_India_Index_Upto_April23__1[[#This Row],[Health]]+All_India_Index_Upto_April23__1[[#This Row],[Fuel and light]]) -> 1712.1119
A11: Urban | B11: 2023 | C11: February | D11: 174.7 | E11: 212.2 | F11: 177.2 | G11: 177.9 | H11: 172.2 | I11: 172.1 | J11: 175.8 | K11: 172.2 | L11: 121.9 | M11: 204.8 | N11: 164.9 | O11: 196.6 | P11: 180.7 | Q11: 202.7 | R11: 180.3 | S11: 167 | T11: 178.2 | U11: 173.5 | V11: 182.8 | W11: 169.2 | X11: 180.8 | Y11: 159.8 | Z11: 168.4 | AA11: 172.5 | AB11: 181.4 | AC11: 170 | AD11: 176.3 | AE11: 178.99286 | AF11: 175.16667 | AG11: 171.35 | AH11: =All_India_Index_Upto_April23__1[[#This Row],[House]]/All_India_Index_Upto_April23__1[[#This Row],[TOTAL BROADER CATEGORIES]] -> 0.098408605 | AI11: =All_India_Index_Upto_April23__1[[#This Row],[Cloth]]/All_India_Index_Upto_April23__1[[#This Row],[TOTAL BROADER CATEGORIES]] -> 0.10060057 | AJ11: =All_India_Index_Upto_April23__1[[#This Row],[Food]]/All_India_Index_Upto_April23__1[[#This Row],[TOTAL BROADER CATEGORIES]] -> 0.102798 | AK11: =All_India_Index_Upto_April23__1[[#This Row],[Miscellaneous]]/All_India_Index_Upto_April23__1[[#This Row],[TOTAL BROADER CATEGORIES]] -> 0.097633282 | AL11: =All_India_Index_Upto_April23__1[[#This Row],[Personal care and effects]]/All_India_Index_Upto_April23__1[[#This Row],[TOTAL BROADER CATEGORIES]] -> 0.10418045 | AM11: =All_India_Index_Upto_April23__1[[#This Row],[Education]]/All_India_Index_Upto_April23__1[[#This Row],[TOTAL BROADER CATEGORIES]] -> 0.099069065 | AN11: =All_India_Index_Upto_April23__1[[#This Row],[Recreation and amusement]]/All_India_Index_Upto_April23__1[[#This Row],[TOTAL BROADER CATEGORIES]] -> 0.09671438 | AO11: =All_India_Index_Upto_April23__1[[#This Row],[Transport and communication]]/All_India_Index_Upto_April23__1[[#This Row],[TOTAL BROADER CATEGORIES]] -> 0.091775285 | AP11: =All_India_Index_Upto_April23__1[[#This Row],[Health]]/All_India_Index_Upto_April23__1[[#This Row],[TOTAL BROADER CATEGORIES]] -> 0.10383587 | AQ11: =All_India_Index_Upto_April23__1[[#This Row],[Fuel and light]]/All_India_Index_Upto_April23__1[[#This Row],[TOTAL BROADER CATEGORIES]] -> 0.10498449 | AR11: =MONTH(1 & All_India_Index_Upto_April23__1[[#This Row],[Month]]) -> 2 | AS11: =All_India_Index_Upto_April23__1[[#This Row],[MONTH IN NUM]]&"/"&All_India_Index_Upto_April23__1[[#This Row],[Year]] -> 2/2023 | AT11: =SUM((All_India_Index_Upto_April23__1[[#This Row],[Education]]+All_India_Index_Upto_April23__1[[#This Row],[Household goods and services]]+All_India_Index_Upto_April23__1[[#This Row],[Fuel and light]]+All_India_Index_Upto_April23__1[[#This Row],[Housing]]+All_India_Index_Upto_April23__1[[#This Row],[Clothing and footwear]]+All_India_Index_Upto_April23__1[[#This Row],[Footwear]]+All_India_Index_Upto_April23__1[[#This Row],[Clothing]])/7) -> 174.78571 | AU11: =(All_India_Index_Upto_April23__1[[#This Row],[House]]+All_India_Index_Upto_April23__1[[#This Row],[Cloth]]+All_India_Index_Upto_April23__1[[#This Row],[Food]]+All_India_Index_Upto_April23__1[[#This Row],[Miscellaneous]]+All_India_Index_Upto_April23__1[[#This Row],[Personal care and effects]]+All_India_Index_Upto_April23__1[[#This Row],[Education]]+All_India_Index_Upto_April23__1[[#This Row],[Recreation and amusement]]+All_India_Index_Upto_April23__1[[#This Row],[Transport and communication]]+All_India_Index_Upto_April23__1[[#This Row],[Health]]+All_India_Index_Upto_April23__1[[#This Row],[Fuel and light]]) -> 1741.2095
A12: Rural+Urban | B12: 2022 | C12: August | D12: 160.3 | E12: 206.5 | F12: 169.2 | G12: 168.1 | H12: 189.675 | I12: 172.9 | J12: 186.7 | K12: 167.2 | L12: 120.9 | M12: 193.6 | N12: 168.8 | O12: 186.3 | P12: 176.3 | Q12: 195 | R12: 179.5 | S12: 172.7 | T12: 178.5 | U12: 169 | V12: 178.8 | W12: 168.5 | X12: 176.8 | Y12: 161.9 | Z12: 166.9 | AA12: 172.3 | AB12: 171.2 | AC12: 169.1 | AD12: 174.3 | AE12: 176.01429 | AF12: 176.9 | AG12: 168.75 | AH12: =All_India_Index_Upto_April23__1[[#This Row],[House]]/All_India_Index_Upto_April23__1[[#This Row],[TOTAL BROADER CATEGORIES]] -> 0.098186715 | AI12: =All_India_Index_Upto_April23__1[[#This Row],[Cloth]]/All_India_Index_Upto_April23__1[[#This Row],[TOTAL BROADER CATEGORIES]] -> 0.10292877 | AJ12: =All_India_Index_Upto_April23__1[[#This Row],[Food]]/All_India_Index_Upto_April23__1[[#This Row],[TOTAL BROADER CATEGORIES]] -> 0.10241342 | AK12: =All_India_Index_Upto_April23__1[[#This Row],[Miscellaneous]]/All_India_Index_Upto_April23__1[[#This Row],[TOTAL BROADER CATEGORIES]] -> 0.098390361 | AL12: =All_India_Index_Upto_April23__1[[#This Row],[Personal care and effects]]/All_India_Index_Upto_April23__1[[#This Row],[TOTAL BROADER CATEGORIES]] -> 0.09961224 | AM12: =All_India_Index_Upto_April23__1[[#This Row],[Education]]/All_India_Index_Upto_April23__1[[#This Row],[TOTAL BROADER CATEGORIES]] -> 0.10025227 | AN12: =All_India_Index_Upto_April23__1[[#This Row],[Recreation and amusement]]/All_India_Index_Upto_April23__1[[#This Row],[TOTAL BROADER CATEGORIES]] -> 0.097110297 | AO12: =All_India_Index_Upto_April23__1[[#This Row],[Transport and communication]]/All_India_Index_Upto_April23__1[[#This Row],[TOTAL BROADER CATEGORIES]] -> 0.094201061 | AP12: =All_India_Index_Upto_April23__1[[#This Row],[Health]]/All_India_Index_Upto_April23__1[[#This Row],[TOTAL BROADER CATEGORIES]] -> 0.10287058 | AQ12: =All_India_Index_Upto_April23__1[[#This Row],[Fuel and light]]/All_India_Index_Upto_April23__1[[#This Row],[TOTAL BROADER CATEGORIES]] -> 0.10403428 | AR12: =MONTH(1 & All_India_Index_Upto_April23__1[[#This Row],[Month]]) -> 8 | AS12: =All_India_Index_Upto_April23__1[[#This Row],[MONTH IN NUM]]&"/"&All_India_Index_Upto_April23__1[[#This Row],[Year]] -> 8/2022 | AT12: =SUM((All_India_Index_Upto_April23__1[[#This Row],[Education]]+All_India_Index_Upto_April23__1[[#This Row],[Household goods and services]]+All_India_Index_Upto_April23__1[[#This Row],[Fuel and light]]+All_India_Index_Upto_April23__1[[#This Row],[Housing]]+All_India_Index_Upto_April23__1[[#This Row],[Clothing and footwear]]+All_India_Index_Upto_April23__1[[#This Row],[Footwear]]+All_India_Index_Upto_April23__1[[#This Row],[Clothing]])/7) -> 174.18571 | AU12: =(All_India_Index_Upto_April23__1[[#This Row],[House]]+All_India_Index_Upto_April23__1[[#This Row],[Cloth]]+All_India_Index_Upto_April23__1[[#This Row],[Food]]+All_India_Index_Upto_April23__1[[#This Row],[Miscellaneous]]+All_India_Index_Upto_April23__1[[#This Row],[Personal care and effects]]+All_India_Index_Upto_April23__1[[#This Row],[Education]]+All_India_Index_Upto_April23__1[[#This Row],[Recreation and amusement]]+All_India_Index_Upto_April23__1[[#This Row],[Transport and communication]]+All_India_Index_Upto_April23__1[[#This Row],[Health]]+All_India_Index_Upto_April23__1[[#This Row],[Fuel and light]]) -> 1718.6643
A13: Rural | B13: 2023 | C13: February | D13: 174.2 | E13: 205.2 | F13: 173.9 | G13: 177 | H13: 183.4 | I13: 167.2 | J13: 140.9 | K13: 170.4 | L13: 119.1 | M13: 212.1 | N13: 177.6 | O13: 189.9 | P13: 174.8 | Q13: 198.3 | R13: 190 | S13: 185.35 | T13: 189.6 | U13: 140.85 | V13: 181.6 | W13: 178.6 | X13: 186.6 | Y13: 169 | Z13: 172.8 | AA13: 178.5 | AB13: 180.7 | AC13: 177.9 | AD13: 178 | AE13: 176 | AF13: 188.86667 | AG13: 159.725 | AH13: =All_India_Index_Upto_April23__1[[#This Row],[House]]/All_India_Index_Upto_April23__1[[#This Row],[TOTAL BROADER CATEGORIES]] -> 0.090153949 | AI13: =All_India_Index_Upto_April23__1[[#This Row],[Cloth]]/All_India_Index_Upto_April23__1[[#This Row],[TOTAL BROADER CATEGORIES]] -> 0.10660245 | AJ13: =All_India_Index_Upto_April23__1[[#This Row],[Food]]/All_India_Index_Upto_April23__1[[#This Row],[TOTAL BROADER CATEGORIES]] -> 0.099340085 | AK13: =All_India_Index_Upto_April23__1[[#This Row],[Miscellaneous]]/All_India_Index_Upto_April23__1[[#This Row],[TOTAL BROADER CATEGORIES]] -> 0.10041251 | AL13: =All_India_Index_Upto_April23__1[[#This Row],[Personal care and effects]]/All_India_Index_Upto_April23__1[[#This Row],[TOTAL BROADER CATEGORIES]] -> 0.10199292 | AM13: =All_India_Index_Upto_April23__1[[#This Row],[Education]]/All_India_Index_Upto_April23__1[[#This Row],[TOTAL BROADER CATEGORIES]] -> 0.10075117 | AN13: =All_India_Index_Upto_April23__1[[#This Row],[Recreation and amusement]]/All_India_Index_Upto_April23__1[[#This Row],[TOTAL BROADER CATEGORIES]] -> 0.097533901 | AO13: =All_India_Index_Upto_April23__1[[#This Row],[Transport and communication]]/All_India_Index_Upto_April23__1[[#This Row],[TOTAL BROADER CATEGORIES]] -> 0.095389058 | AP13: =All_India_Index_Upto_April23__1[[#This Row],[Health]]/All_India_Index_Upto_April23__1[[#This Row],[TOTAL BROADER CATEGORIES]] -> 0.10532307 | AQ13: =All_India_Index_Upto_April23__1[[#This Row],[Fuel and light]]/All_India_Index_Upto_April23__1[[#This Row],[TOTAL BROADER CATEGORIES]] -> 0.10250091 | AR13: =MONTH(1 & All_India_Index_Upto_April23__1[[#This Row],[Month]]) -> 2 | AS13: =All_India_Index_Upto_April23__1[[#This Row],[MONTH IN NUM]]&"/"&All_India_Index_Upto_April23__1[[#This Row],[Year]] -> 2/2023 | AT13: =SUM((All_India_Index_Upto_April23__1[[#This Row],[Education]]+All_India_Index_Upto_April23__1[[#This Row],[Household goods and services]]+All_India_Index_Upto_April23__1[[#This Row],[Fuel and light]]+All_India_Index_Upto_April23__1[[#This Row],[Housing]]+All_India_Index_Upto_April23__1[[#This Row],[Clothing and footwear]]+All_India_Index_Upto_April23__1[[#This Row],[Footwear]]+All_India_Index_Upto_April23__1[[#This Row],[Clothing]])/7) -> 177.78571 | AU13: =(All_India_Index_Upto_April23__1[[#This Row],[House]]+All_India_Index_Upto_April23__1[[#This Row],[Cloth]]+All_India_Index_Upto_April23__1[[#This Row],[Food]]+All_India_Index_Upto_April23__1[[#This Row],[Miscellaneous]]+All_India_Index_Upto_April23__1[[#This Row],[Personal care and effects]]+All_India_Index_Upto_April23__1[[#This Row],[Education]]+All_India_Index_Upto_April23__1[[#This Row],[Recreation and amusement]]+All_India_Index_Upto_April23__1[[#This Row],[Transport and communication]]+All_India_Index_Upto_April23__1[[#This Row],[Health]]+All_India_Index_Upto_April23__1[[#This Row],[Fuel and light]]) -> 1771.6917
... A367: Urban | B367: 2013 | C367: January | D367: 110.5 | E367: 109.1 | F367: 113 | G367: 103.6 | H367: 103.4 | I367: 102.3 | J367: 102.9 | K367: 105.8 | L367: 105.1 | M367: 101.8 | N367: 105.1 | O367: 107.9 | P367: 105.9 | Q367: 105.2 | R367: 105.9 | S367: 105 | T367: 105.8 | U367: 100.3 | V367: 105.4 | W367: 104.8 | X367: 104.1 | Y367: 103.2 | Z367: 102.9 | AA367: 103.5 | AB367: 104.3 | AC367: 103.7 | AD367: 104 | AE367: 105.82857 | AF367: 105.56667 | AG367: 102.55 | AH367: =All_India_Index_Upto_April23__1[[#This Row],[House]]/All_India_Index_Upto_April23__1[[#This Row],[TOTAL BROADER CATEGORIES]] -> 0.098506766 | AI367: =All_India_Index_Upto_April23__1[[#This Row],[Cloth]]/All_India_Index_Upto_April23__1[[#This Row],[TOTAL BROADER CATEGORIES]] -> 0.1014045 | AJ367: =All_India_Index_Upto_April23__1[[#This Row],[Food]]/All_India_Index_Upto_April23__1[[#This Row],[TOTAL BROADER CATEGORIES]] -> 0.10165607 | AK367: =All_India_Index_Upto_April23__1[[#This Row],[Miscellaneous]]/All_India_Index_Upto_April23__1[[#This Row],[TOTAL BROADER CATEGORIES]] -> 0.099611425 | AL367: =All_India_Index_Upto_April23__1[[#This Row],[Personal care and effects]]/All_India_Index_Upto_April23__1[[#This Row],[TOTAL BROADER CATEGORIES]] -> 0.10018777 | AM367: =All_India_Index_Upto_April23__1[[#This Row],[Education]]/All_India_Index_Upto_April23__1[[#This Row],[TOTAL BROADER CATEGORIES]] -> 0.099419311 | AN367: =All_India_Index_Upto_April23__1[[#This Row],[Recreation and amusement]]/All_India_Index_Upto_April23__1[[#This Row],[TOTAL BROADER CATEGORIES]] -> 0.098842967 | AO367: =All_India_Index_Upto_April23__1[[#This Row],[Transport and communication]]/All_India_Index_Upto_April23__1[[#This Row],[TOTAL BROADER CATEGORIES]] -> 0.099131139 | AP367: =All_India_Index_Upto_April23__1[[#This Row],[Health]]/All_India_Index_Upto_April23__1[[#This Row],[TOTAL BROADER CATEGORIES]] -> 0.099995655 | AQ367: =All_India_Index_Upto_April23__1[[#This Row],[Fuel and light]]/All_India_Index_Upto_April23__1[[#This Row],[TOTAL BROADER CATEGORIES]] -> 0.1012444 | AR367: =MONTH(1 & All_India_Index_Upto_April23__1[[#This Row],[Month]]) -> 1 | AS367: =All_India_Index_Upto_April23__1[[#This Row],[MONTH IN NUM]]&"/"&All_India_Index_Upto_April23__1[[#This Row],[Year]] -> 1/2013 | AT367: =SUM((All_India_Index_Upto_April23__1[[#This Row],[Education]]+All_India_Index_Upto_April23__1[[#This Row],[Household goods and services]]+All_India_Index_Upto_April23__1[[#This Row],[Fuel and light]]+All_India_Index_Upto_April23__1[[#This Row],[Housing]]+All_India_Index_Upto_April23__1[[#This Row],[Clothing and footwear]]+All_India_Index_Upto_April23__1[[#This Row],[Footwear]]+All_India_Index_Upto_April23__1[[#This Row],[Clothing]])/7) -> 104.38571 | AU367: =(All_India_Index_Upto_April23__1[[#This Row],[House]]+All_India_Index_Upto_April23__1[[#This Row],[Cloth]]+All_India_Index_Upto_April23__1[[#This Row],[Food]]+All_India_Index_Upto_April23__1[[#This Row],[Miscellaneous]]+All_India_Index_Upto_April23__1[[#This Row],[Personal care and effects]]+All_India_Index_Upto_April23__1[[#This Row],[Education]]+All_India_Index_Upto_April23__1[[#This Row],[Recreation and amusement]]+All_India_Index_Upto_April23__1[[#This Row],[Transport and communication]]+All_India_Index_Upto_April23__1[[#This Row],[Health]]+All_India_Index_Upto_April23__1[[#This Row],[Fuel and light]]) -> 1041.0452

Sheet BROADER CATEGORY SOL
A1: CONTRIBUTION | B1: RURAL | C1: URBAN | D1: Rural+Urban
A2: CONTRIBUTION IN HOUSE | B2: =SUMIFS('BROADER CATEGORIES'!$AH:$AH,'BROADER CATEGORIES'!$A:$A,"Rural",'BROADER CATEGORIES'!$AS:$AS,"05/2023") -> 0.089732886 | C2: =SUMIFS('BROADER CATEGORIES'!$AH:$AH,'BROADER CATEGORIES'!$A:$A,"Urban",'BROADER CATEGORIES'!$AS:$AS,"5/2023") -> 0.098340869 | D2: =SUMIFS('BROADER CATEGORIES'!$AH:$AH,'BROADER CATEGORIES'!$A:$A,"Rural+Urban",'BROADER CATEGORIES'!AS:AS,"5/2023") -> 0.09845991
A3: CONTRIBUTION IN CLOTH | B3: =SUMIFS('BROADER CATEGORIES'!$AI:$AI,'BROADER CATEGORIES'!$A:$A,"Rural",'BROADER CATEGORIES'!$AS:$AS,"05/2023") -> 0.10632314 | C3: =SUMIFS('BROADER CATEGORIES'!$AI:$AI,'BROADER CATEGORIES'!$A:$A,"Urban",'BROADER CATEGORIES'!$AS:$AS,"5/2023") -> 0.10026578 | D3: =SUMIFS('BROADER CATEGORIES'!$AI:$AI,'BROADER CATEGORIES'!$A:$A,"Rural+Urban",'BROADER CATEGORIES'!AS:AS,"5/2023") -> 0.10351201
A4: CONTRIBUTION IN FOOD | B4: =SUMIFS('BROADER CATEGORIES'!$AJ:$AJ,'BROADER CATEGORIES'!$A:$A,"Rural",'BROADER CATEGORIES'!$AS:$AS,"05/2023") -> 0.099569502 | C4: =SUMIFS('BROADER CATEGORIES'!$AJ:$AJ,'BROADER CATEGORIES'!$A:$A,"Urban",'BROADER CATEGORIES'!$AS:$AS,"5/2023") -> 0.10319309 | D4: =SUMIFS('BROADER CATEGORIES'!$AJ:$AJ,'BROADER CATEGORIES'!$A:$A,"Rural+Urban",'BROADER CATEGORIES'!AS:AS,"5/2023") -> 0.10055693
A5: CONTRIBUTION IN MIS_ITEM | B5: =SUMIFS('BROADER CATEGORIES'!$AK:$AK,'BROADER CATEGORIES'!$A:$A,"Rural",'BROADER CATEGORIES'!$AS:$AS,"05/2023") -> 0.10046501 | C5: =SUMIFS('BROADER CATEGORIES'!$AK:$AK,'BROADER CATEGORIES'!$A:$A,"Urban",'BROADER CATEGORIES'!$AS:$AS,"5/2023") -> 0.097629697 | D5: =SUMIFS('BROADER CATEGORIES'!$AK:$AK,'BROADER CATEGORIES'!$A:$A,"Rural+Urban",'BROADER CATEGORIES'!AS:AS,"5/2023") -> 0.098628313
A6: CONTRIBUTION IN PER_CARE_ITEM | B6: =SUMIFS('BROADER CATEGORIES'!$AL:$AL,'BROADER CATEGORIES'!$A:$A,"Rural",'BROADER CATEGORIES'!$AS:$AS,"05/2023") -> 0.10348736 | C6: =SUMIFS('BROADER CATEGORIES'!$AL:$AL,'BROADER CATEGORIES'!$A:$A,"Urban",'BROADER CATEGORIES'!$AS:$AS,"5/2023") -> 0.10559482 | D6: =SUMIFS('BROADER CATEGORIES'!$AL:$AL,'BROADER CATEGORIES'!$A:$A,"Rural+Urban",'BROADER CATEGORIES'!AS:AS,"5/2023") -> 0.10396109
A7: CONTRIBUTION IN EDUCATION | B7: =SUMIFS('BROADER CATEGORIES'!$AM:$AM,'BROADER CATEGORIES'!$A:$A,"Rural",'BROADER CATEGORIES'!$AS:$AS,"05/2023") -> 0.10091277 | C7: =SUMIFS('BROADER CATEGORIES'!$AM:$AM,'BROADER CATEGORIES'!$A:$A,"Urban",'BROADER CATEGORIES'!$AS:$AS,"5/2023") -> 0.099450298 | D7: =SUMIFS('BROADER CATEGORIES'!$AM:$AM,'BROADER CATEGORIES'!$A:$A,"Rural+Urban",'BROADER CATEGORIES'!AS:AS,"5/2023") -> 0.099414196
A8: CONTRIBUTION IN REC_AND_AMU | B8: =SUMIFS('BROADER CATEGORIES'!$AN:$AN,'BROADER CATEGORIES'!$A:$A,"Rural",'BROADER CATEGORIES'!$AS:$AS,"05/2023") -> 0.097274758 | C8: =SUMIFS('BROADER CATEGORIES'!$AN:$AN,'BROADER CATEGORIES'!$A:$A,"Urban",'BROADER CATEGORIES'!$AS:$AS,"5/2023") -> 0.096264247 | D8: =SUMIFS('BROADER CATEGORIES'!$AN:$AN,'BROADER CATEGORIES'!$A:$A,"Rural+Urban",'BROADER CATEGORIES'!AS:AS,"5/2023") -> 0.096102261
A9: CONTRIBUTION IN TR_COM | B9: =SUMIFS('BROADER CATEGORIES'!$AO:$AO,'BROADER CATEGORIES'!$A:$A,"Rural",'BROADER CATEGORIES'!$AS:$AS,"05/2023") -> 0.094980014 | C9: =SUMIFS('BROADER CATEGORIES'!$AO:$AO,'BROADER CATEGORIES'!$A:$A,"Urban",'BROADER CATEGORIES'!$AS:$AS,"5/2023") -> 0.091257596 | D9: =SUMIFS('BROADER CATEGORIES'!$AO:$AO,'BROADER CATEGORIES'!$A:$A,"Rural+Urban",'BROADER CATEGORIES'!AS:AS,"5/2023") -> 0.092509653
A10: CONTRIBUTION IN HEALTH | B10: =SUMIFS('BROADER CATEGORIES'!$AP:$AP,'BROADER CATEGORIES'!$A:$A,"Rural",'BROADER CATEGORIES'!$AS:$AS,"05/2023") -> 0.10511047 | C10: =SUMIFS('BROADER CATEGORIES'!$AP:$AP,'BROADER CATEGORIES'!$A:$A,"Urban",'BROADER CATEGORIES'!$AS:$AS,"5/2023") -> 0.10366044 | D10: =SUMIFS('BROADER CATEGORIES'!$AP:$AP,'BROADER CATEGORIES'!$A:$A,"Rural+Urban",'BROADER CATEGORIES'!AS:AS,"5/2023") -> 0.10424176
A11: CONTRIBUTION IN L&F | B11: =SUMIFS('BROADER CATEGORIES'!$AQ:$AQ,'BROADER CATEGORIES'!$A:$A,"Rural",'BROADER CATEGORIES'!$AS:$AS,"05/2023") -> 0.10214409 | C11: =SUMIFS('BROADER CATEGORIES'!$AQ:$AQ,'BROADER CATEGORIES'!$A:$A,"Urban",'BROADER CATEGORIES'!$AS:$AS,"5/2023") -> 0.10434316 | D11: =SUMIFS('BROADER CATEGORIES'!$AQ:$AQ,'BROADER CATEGORIES'!$A:$A,"Rural+Urban",'BROADER CATEGORIES'!AS:AS,"5/2023") -> 0.10261386
A12: TOTAL | B12: =SUM(B2:B11) -> 1 | C12: =SUM(C2:C11) -> 1 | D12: =SUM(D2:D11) -> 1
A13: Highest contributor | B13: =INDEX(A2:A11,MATCH(MAX(B2:B11),B2:B11,0)) -> CONTRIBUTION IN CLOTH | C13: =INDEX($A$2:$A$11,MATCH(MAX(C$2:C$11),C$2:C$11,0)) -> CONTRIBUTION IN PER_CARE_ITEM | D13: =INDEX(A2:A11,MATCH(MAX(D2:D11),D2:D11,0)) -> CONTRIBUTION IN HEALTH
A14: Maximum Contribution | B14: =MAX(B2:B11) -> 0.10632314 | C14: =MAX(C2:C11) -> 0.10559482 | D14: =MAX(D2:D11) -> 0.10424176
A18: Dominance of Service Inflation (Health): Nationally, Health (10.42%) is the top contributor. | B18: Sectoral Disparity (Clothing vs. Personal Care): | C18: The "Food" Relief: Food (9.86%) is ranked lower (#7). | D18: Housing Stability: Housing (9.23%) is at the bottom (Rank 10).
A19: NSO Insight: This indicates "Service-led Inflation." Unlike volatile food prices, healthcare inflation is "sticky" and harder to control. It suggests a rising cost of essential medical services across both Rural and Urban sectors. | B19: Rural Insight: Clothing (10.65%) is the highest driver in Rural areas. This could be due to supply-side bottlenecks or higher logistics costs reaching remote areas. | C19: NSO Insight: For a country like India, where Food has the highest weightage, its lower contribution in May 2023 is a positive sign for "Food Security" and indicates stable agricultural supply chains for that period. | D19: NSO Insight: This suggests that "Core Inflation" (excluding food and fuel) is being balanced by stable urban rentals, providing some relief to the middle class.
B20: Urban Insight: Personal Care (10.56%) leads in Urban areas, reflecting a shift in consumption patterns where lifestyle and grooming products are pushing the CPI higher.
A25: Categories | B25: Rural | C25: Urban | D25: Rural+Urban | E25: Rank
A26: =INDEX($A$2:$A$11,MATCH(B26,$B$2:$B$11,0)) -> CONTRIBUTION IN CLOTH | B26: =LARGE($B$2:$B$11,$E26) -> 0.10632314 | C26: =LARGE($C$2:$C$11,$E26) -> 0.10559482 | D26: =LARGE($D$2:$D$11,$E26) -> 0.10424176 | E26: 1
A27: =INDEX($A$2:$A$11,MATCH(B27,$B$2:$B$11,0)) -> CONTRIBUTION IN HEALTH | B27: =LARGE($B$2:$B$11,$E27) -> 0.10511047 | C27: =LARGE($C$2:$C$11,$E27) -> 0.10434316 | D27: =LARGE($D$2:$D$11,$E27) -> 0.10396109 | E27: 2
A28: =INDEX($A$2:$A$11,MATCH(B28,$B$2:$B$11,0)) -> CONTRIBUTION IN PER_CARE_ITEM | B28: =LARGE($B$2:$B$11,$E28) -> 0.10348736 | C28: =LARGE($C$2:$C$11,$E28) -> 0.10366044 | D28: =LARGE($D$2:$D$11,$E28) -> 0.10351201 | E28: 3 | H28: Policy Recommendations (The "Analyst" Move)
A29: =INDEX($A$2:$A$11,MATCH(B29,$B$2:$B$11,0)) -> CONTRIBUTION IN L&F | B29: =LARGE($B$2:$B$11,$E29) -> 0.10214409 | C29: =LARGE($C$2:$C$11,$E29) -> 0.10319309 | D29: =LARGE($D$2:$D$11,$E29) -> 0.10261386 | E29: 4
A30: =INDEX($A$2:$A$11,MATCH(B30,$B$2:$B$11,0)) -> CONTRIBUTION IN EDUCATION | B30: =LARGE($B$2:$B$11,$E30) -> 0.10091277 | C30: =LARGE($C$2:$C$11,$E30) -> 0.10026578 | D30: =LARGE($D$2:$D$11,$E30) -> 0.10055693 | E30: 5 | H30: 1. Monitor Healthcare Costs: Suggesting a deeper look into pharmaceutical pricing as it's the primary inflation driver.
A31: =INDEX($A$2:$A$11,MATCH(B31,$B$2:$B$11,0)) -> CONTRIBUTION IN MIS_ITEM | B31: =LARGE($B$2:$B$11,$E31) -> 0.10046501 | C31: =LARGE($C$2:$C$11,$E31) -> 0.099450298 | D31: =LARGE($D$2:$D$11,$E31) -> 0.099414196 | E31: 6 | H31: 2. Rural Logistics: Investigating why Clothing is significantly higher in Rural areas—is it a transport cost issue or a demand surge?
A32: =INDEX($A$2:$A$11,MATCH(B32,$B$2:$B$11,0)) -> CONTRIBUTION IN FOOD | B32: =LARGE($B$2:$B$11,$E32) -> 0.099569502 | C32: =LARGE($C$2:$C$11,$E32) -> 0.098340869 | D32: =LARGE($D$2:$D$11,$E32) -> 0.098628313 | E32: 7 | H32: 3. RBI Intervention: Since 'Miscellaneous' (Services) inflation is high, the RBI might need to maintain a "Hawkish" (strict) stance on interest rates to cool down demand.
A33: =INDEX($A$2:$A$11,MATCH(B33,$B$2:$B$11,0)) -> CONTRIBUTION IN REC_AND_AMU | B33: =LARGE($B$2:$B$11,$E33) -> 0.097274758 | C33: =LARGE($C$2:$C$11,$E33) -> 0.097629697 | D33: =LARGE($D$2:$D$11,$E33) -> 0.09845991 | E33: 8
A34: =INDEX($A$2:$A$11,MATCH(B34,$B$2:$B$11,0)) -> CONTRIBUTION IN TR_COM | B34: =LARGE($B$2:$B$11,$E34) -> 0.094980014 | C34: =LARGE($C$2:$C$11,$E34) -> 0.096264247 | D34: =LARGE($D$2:$D$11,$E34) -> 0.096102261 | E34: 9
A35: =INDEX($A$2:$A$11,MATCH(B35,$B$2:$B$11,0)) -> CONTRIBUTION IN HOUSE | B35: =LARGE($B$2:$B$11,$E35) -> 0.089732886 | C35: =LARGE($C$2:$C$11,$E35) -> 0.091257596 | D35: =LARGE($D$2:$D$11,$E35) -> 0.092509653 | E35: 10

Sheet Y-O-Y HIGHER INF RATE
A2: Sector | B2: Rural+Urban
A4: Row Labels | B4: Average of General index
A5: 2016
A6: 2017 | B6: 0.033281734
A7: 2018 | B7: 0.039513109
A8: 2019 | B8: 0.038961039
A9: 2020 | B9: 0.063795712
A10: 2021 | B10: 0.052668753
A11: 2022 | B11: 0.066219355
A12: Grand Total
A23: 2020 Peak: Spike to 6.38% due to COVID-19 supply chain disruptions.
A24: 2021 Cooling: Dip to 5.27% due to base effects and suppressed demand.
A25: 2022 Surge: Global energy crisis pushed inflation to a 6-year high of 6.62%.

Sheet M-O-M HIGH & LOW INF
A2: MOM INFLATION RATE
A3: DATE | B3: FOOD GI | C3: M-O-M PER
A4: =All_India_Index_Upto_April23__1[[#This Row],[CONCAT Y&M]] -> 5/2022 | B4: =SUMIFS('BROADER CATEGORIES'!$AE:$AE,'BROADER CATEGORIES'!$A:$A,"Rural+Urban",'BROADER CATEGORIES'!$AS:$AS,'M-O-M HIGH & LOW INF'!A4) -> 173.78571 | C4: N/A
A5: =All_India_Index_Upto_April23__1[[#This Row],[CONCAT Y&M]] -> 6/2022 | B5: =SUMIFS('BROADER CATEGORIES'!$AE:$AE,'BROADER CATEGORIES'!$A:$A,"Rural+Urban",'BROADER CATEGORIES'!$AS:$AS,'M-O-M HIGH & LOW INF'!A5) -> 175.44286 | C5: =(B5-B4)/B4 -> 0.0095355528
A6: ='BROADER CATEGORIES'!AS10 -> 7/2022 | B6: =SUMIFS('BROADER CATEGORIES'!$AE:$AE,'BROADER CATEGORIES'!$A:$A,"Rural+Urban",'BROADER CATEGORIES'!$AS:$AS,'M-O-M HIGH & LOW INF'!A6) -> 175.77857 | C6: =(B6-B5)/B5 -> 0.001913525
A7: ='BROADER CATEGORIES'!AS12 -> 8/2022 | B7: =SUMIFS('BROADER CATEGORIES'!$AE:$AE,'BROADER CATEGORIES'!$A:$A,"Rural+Urban",'BROADER CATEGORIES'!$AS:$AS,'M-O-M HIGH & LOW INF'!A7) -> 176.01429 | C7: =(B7-B6)/B6 -> 0.0013409728
A8: ='BROADER CATEGORIES'!AS16 -> 9/2022 | B8: =SUMIFS('BROADER CATEGORIES'!$AE:$AE,'BROADER CATEGORIES'!$A:$A,"Rural+Urban",'BROADER CATEGORIES'!$AS:$AS,'M-O-M HIGH & LOW INF'!A8) -> 176.91429 | C8: =(B8-B7)/B7 -> 0.0051132213
A9: ='BROADER CATEGORIES'!AS18 -> 10/2022 | B9: =SUMIFS('BROADER CATEGORIES'!$AE:$AE,'BROADER CATEGORIES'!$A:$A,"Rural+Urban",'BROADER CATEGORIES'!$AS:$AS,'M-O-M HIGH & LOW INF'!A9) -> 178.11429 | C9: =(B9-B8)/B8 -> 0.0067829457
A10: ='BROADER CATEGORIES'!AS20 -> 11/2022 | B10: =SUMIFS('BROADER CATEGORIES'!$AE:$AE,'BROADER CATEGORIES'!$A:$A,"Rural+Urban",'BROADER CATEGORIES'!$AS:$AS,'M-O-M HIGH & LOW INF'!A10) -> 178.12143 | C10: =(B10-B9)/B9 -> 4.0102663e-05
A11: ='BROADER CATEGORIES'!AS17 -> 12/2022 | B11: =SUMIFS('BROADER CATEGORIES'!$AE:$AE,'BROADER CATEGORIES'!$A:$A,"Rural+Urban",'BROADER CATEGORIES'!$AS:$AS,'M-O-M HIGH & LOW INF'!A11) -> 177.19286 | C11: =(B11-B10)/B10 -> -0.0052131371
A12: ='BROADER CATEGORIES'!AS14 -> 1/2023 | B12: =SUMIFS('BROADER CATEGORIES'!$AE:$AE,'BROADER CATEGORIES'!$A:$A,"Rural+Urban",'BROADER CATEGORIES'!$AS:$AS,'M-O-M HIGH & LOW INF'!A12) -> 177.92143 | C12: =(B12-B11)/B11 -> 0.0041117427
A13: ='BROADER CATEGORIES'!AS11 -> 2/2023 | B13: =SUMIFS('BROADER CATEGORIES'!$AE:$AE,'BROADER CATEGORIES'!$A:$A,"Rural+Urban",'BROADER CATEGORIES'!$AS:$AS,'M-O-M HIGH & LOW INF'!A13) -> 177.04286 | C13: =(B13-B12)/B12 -> -0.0049379742
A14: ='BROADER CATEGORIES'!AS8 -> 3/2023 | B14: =SUMIFS('BROADER CATEGORIES'!$AE:$AE,'BROADER CATEGORIES'!$A:$A,"Rural+Urban",'BROADER CATEGORIES'!$AS:$AS,'M-O-M HIGH & LOW INF'!A14) -> 177.05 | C14: =(B14-B13)/B13 -> 4.0345356e-05
A15: ='BROADER CATEGORIES'!AS6 -> 4/2023 | B15: =SUMIFS('BROADER CATEGORIES'!$AE:$AE,'BROADER CATEGORIES'!$A:$A,"Rural+Urban",'BROADER CATEGORIES'!$AS:$AS,'M-O-M HIGH & LOW INF'!A15) -> 177.87143 | C15: =(B15-B14)/B14 -> 0.0046395288
A16: ='BROADER CATEGORIES'!AS2 -> 5/2023 | B16: =SUMIFS('BROADER CATEGORIES'!$AE:$AE,'BROADER CATEGORIES'!$A:$A,"Rural+Urban",'BROADER CATEGORIES'!$AS:$AS,'M-O-M HIGH & LOW INF'!A16) -> 179.13571 | C16: =(B16-B15)/B15 -> 0.0071078628
A19: This was a "Supply-Side Shock" caused by global heatwaves impacting crop yields and a sudden surge in edible oil prices. Such a high MoM increase indicates an immediate and severe pressure on the consumer's kitchen budget. | B19: June 2022 recorded a massive MoM spike of 0.95%, which is an abnormal deviation from the usual 1-2% range.
A32: FOOD SUB CATEGORIES | B32: ='BROADER CATEGORIES'!AR4&"/"&'BROADER CATEGORIES'!B4 -> 5/2022 | C32: ='BROADER CATEGORIES'!AR2&"/"&'BROADER CATEGORIES'!B2 -> 5/2023 | D32: ABSOLUTE CHANGE | E32: PER CHANGE
A33: Cereals and products | B33: =INDEX(All_India_Index_Upto_April23__1[#All],MATCH('M-O-M HIGH & LOW INF'!B$32,All_India_Index_Upto_April23__1[[#All],[CONCAT Y&M]],0),MATCH('M-O-M HIGH & LOW INF'!$A33,All_India_Index_Upto_April23__1[#Headers],0)) -> 154.1 | C33: =INDEX(All_India_Index_Upto_April23__1[#All],MATCH('M-O-M HIGH & LOW INF'!C$32,All_India_Index_Upto_April23__1[[#All],[CONCAT Y&M]],0),MATCH('M-O-M HIGH & LOW INF'!A33,All_India_Index_Upto_April23__1[#Headers],0)) -> 173.2 | D33: =C33-B33 -> 19.1 | E33: =(C33-B33)/B33 -> 0.12394549
A34: Meat and fish | B34: =INDEX(All_India_Index_Upto_April23__1[#All],MATCH('M-O-M HIGH & LOW INF'!B$32,All_India_Index_Upto_April23__1[[#All],[CONCAT Y&M]],0),MATCH('M-O-M HIGH & LOW INF'!$A34,All_India_Index_Upto_April23__1[#Headers],0)) -> 217 | C34: =INDEX(All_India_Index_Upto_April23__1[#All],MATCH('M-O-M HIGH & LOW INF'!C$32,All_India_Index_Upto_April23__1[[#All],[CONCAT Y&M]],0),MATCH('M-O-M HIGH & LOW INF'!A34,All_India_Index_Upto_April23__1[#Headers],0)) -> 211.5 | D34: =C34-B34 -> -5.5 | E34: =(C34-B34)/B34 -> -0.025345622
A35: Egg | B35: =INDEX(All_India_Index_Upto_April23__1[#All],MATCH('M-O-M HIGH & LOW INF'!B$32,All_India_Index_Upto_April23__1[[#All],[CONCAT Y&M]],0),MATCH('M-O-M HIGH & LOW INF'!$A35,All_India_Index_Upto_April23__1[#Headers],0)) -> 162.4 | C35: =INDEX(All_India_Index_Upto_April23__1[#All],MATCH('M-O-M HIGH & LOW INF'!C$32,All_India_Index_Upto_April23__1[[#All],[CONCAT Y&M]],0),MATCH('M-O-M HIGH & LOW INF'!A35,All_India_Index_Upto_April23__1[#Headers],0)) -> 171 | D35: =C35-B35 -> 8.6 | E35: =(C35-B35)/B35 -> 0.052955665
A36: Milk and products | B36: =INDEX(All_India_Index_Upto_April23__1[#All],MATCH('M-O-M HIGH & LOW INF'!B$32,All_India_Index_Upto_April23__1[[#All],[CONCAT Y&M]],0),MATCH('M-O-M HIGH & LOW INF'!$A36,All_India_Index_Upto_April23__1[#Headers],0)) -> 164.9 | C36: =INDEX(All_India_Index_Upto_April23__1[#All],MATCH('M-O-M HIGH & LOW INF'!C$32,All_India_Index_Upto_April23__1[[#All],[CONCAT Y&M]],0),MATCH('M-O-M HIGH & LOW INF'!A36,All_India_Index_Upto_April23__1[#Headers],0)) -> 179.6 | D36: =C36-B36 -> 14.7 | E36: =(C36-B36)/B36 -> 0.089144936
A37: Oils and fats | B37: =INDEX(All_India_Index_Upto_April23__1[#All],MATCH('M-O-M HIGH & LOW INF'!B$32,All_India_Index_Upto_April23__1[[#All],[CONCAT Y&M]],0),MATCH('M-O-M HIGH & LOW INF'!$A37,All_India_Index_Upto_April23__1[#Headers],0)) -> 189.675 | C37: =INDEX(All_India_Index_Upto_April23__1[#All],MATCH('M-O-M HIGH & LOW INF'!C$32,All_India_Index_Upto_April23__1[[#All],[CONCAT Y&M]],0),MATCH('M-O-M HIGH & LOW INF'!A37,All_India_Index_Upto_April23__1[#Headers],0)) -> 173.3 | D37: =C37-B37 -> -16.375 | E37: =(C37-B37)/B37 -> -0.086331883
A38: Fruits | B38: =INDEX(All_India_Index_Upto_April23__1[#All],MATCH('M-O-M HIGH & LOW INF'!B$32,All_India_Index_Upto_April23__1[[#All],[CONCAT Y&M]],0),MATCH('M-O-M HIGH & LOW INF'!$A38,All_India_Index_Upto_April23__1[#Headers],0)) -> 171 | C38: =INDEX(All_India_Index_Upto_April23__1[#All],MATCH('M-O-M HIGH & LOW INF'!C$32,All_India_Index_Upto_April23__1[[#All],[CONCAT Y&M]],0),MATCH('M-O-M HIGH & LOW INF'!A38,All_India_Index_Upto_April23__1[#Headers],0)) -> 169 | D38: =C38-B38 -> -2 | E38: =(C38-B38)/B38 -> -0.011695906
A39: Vegetables | B39: =INDEX(All_India_Index_Upto_April23__1[#All],MATCH('M-O-M HIGH & LOW INF'!B$32,All_India_Index_Upto_April23__1[[#All],[CONCAT Y&M]],0),MATCH('M-O-M HIGH & LOW INF'!$A39,All_India_Index_Upto_April23__1[#Headers],0)) -> 174.9 | C39: =INDEX(All_India_Index_Upto_April23__1[#All],MATCH('M-O-M HIGH & LOW INF'!C$32,All_India_Index_Upto_April23__1[[#All],[CONCAT Y&M]],0),MATCH('M-O-M HIGH & LOW INF'!A39,All_India_Index_Upto_April23__1[#Headers],0)) -> 148.7 | D39: =C39-B39 -> -26.2 | E39: =(C39-B39)/B39 -> -0.14979989
A40: Pulses and products | B40: =INDEX(All_India_Index_Upto_April23__1[#All],MATCH('M-O-M HIGH & LOW INF'!B$32,All_India_Index_Upto_April23__1[[#All],[CONCAT Y&M]],0),MATCH('M-O-M HIGH & LOW INF'!$A40,All_India_Index_Upto_April23__1[#Headers],0)) -> 164.7 | C40: =INDEX(All_India_Index_Upto_April23__1[#All],MATCH('M-O-M HIGH & LOW INF'!C$32,All_India_Index_Upto_April23__1[[#All],[CONCAT Y&M]],0),MATCH('M-O-M HIGH & LOW INF'!A40,All_India_Index_Upto_April23__1[#Headers],0)) -> 174.9 | D40: =C40-B40 -> 10.2 | E40: =(C40-B40)/B40 -> 0.061930783
A41: Sugar and Confectionery | B41: =INDEX(All_India_Index_Upto_April23__1[#All],MATCH('M-O-M HIGH & LOW INF'!B$32,All_India_Index_Upto_April23__1[[#All],[CONCAT Y&M]],0),MATCH('M-O-M HIGH & LOW INF'!$A41,All_India_Index_Upto_April23__1[#Headers],0)) -> 119.7 | C41: =INDEX(All_India_Index_Upto_April23__1[#All],MATCH('M-O-M HIGH & LOW INF'!C$32,All_India_Index_Upto_April23__1[[#All],[CONCAT Y&M]],0),MATCH('M-O-M HIGH & LOW INF'!A41,All_India_Index_Upto_April23__1[#Headers],0)) -> 121.9 | D41: =C41-B41 -> 2.2 | E41: =(C41-B41)/B41 -> 0.018379282
A42: Spices | B42: =INDEX(All_India_Index_Upto_April23__1[#All],MATCH('M-O-M HIGH & LOW INF'!B$32,All_India_Index_Upto_April23__1[[#All],[CONCAT Y&M]],0),MATCH('M-O-M HIGH & LOW INF'!$A42,All_India_Index_Upto_April23__1[#Headers],0)) -> 184.9 | C42: =INDEX(All_India_Index_Upto_April23__1[#All],MATCH('M-O-M HIGH & LOW INF'!C$32,All_India_Index_Upto_April23__1[[#All],[CONCAT Y&M]],0),MATCH('M-O-M HIGH & LOW INF'!A42,All_India_Index_Upto_April23__1[#Headers],0)) -> 213.04 | D42: =C42-B42 -> 28.14 | E42: =(C42-B42)/B42 -> 0.15219037
A43: Non-alcoholic beverages | B43: =INDEX(All_India_Index_Upto_April23__1[#All],MATCH('M-O-M HIGH & LOW INF'!B$32,All_India_Index_Upto_April23__1[[#All],[CONCAT Y&M]],0),MATCH('M-O-M HIGH & LOW INF'!$A43,All_India_Index_Upto_April23__1[#Headers],0)) -> 167.1 | C43: =INDEX(All_India_Index_Upto_April23__1[#All],MATCH('M-O-M HIGH & LOW INF'!C$32,All_India_Index_Upto_April23__1[[#All],[CONCAT Y&M]],0),MATCH('M-O-M HIGH & LOW INF'!A43,All_India_Index_Upto_April23__1[#Headers],0)) -> 178.7 | D43: =C43-B43 -> 11.6 | E43: =(C43-B43)/B43 -> 0.069419509
A44: Prepared meals, snacks, sweets etc. | B44: =INDEX(All_India_Index_Upto_April23__1[#All],MATCH('M-O-M HIGH & LOW INF'!B$32,All_India_Index_Upto_April23__1[[#All],[CONCAT Y&M]],0),MATCH('M-O-M HIGH & LOW INF'!$A44,All_India_Index_Upto_April23__1[#Headers],0)) -> 182.5 | C44: =INDEX(All_India_Index_Upto_April23__1[#All],MATCH('M-O-M HIGH & LOW INF'!C$32,All_India_Index_Upto_April23__1[[#All],[CONCAT Y&M]],0),MATCH('M-O-M HIGH & LOW INF'!A44,All_India_Index_Upto_April23__1[#Headers],0)) -> 191.1 | D44: =C44-B44 -> 8.6 | E44: =(C44-B44)/B44 -> 0.047123288
... A46: Pan, tobacco and intoxicants | B46: =INDEX(All_India_Index_Upto_April23__1[#All],MATCH('M-O-M HIGH & LOW INF'!B$32,All_India_Index_Upto_April23__1[[#All],[CONCAT Y&M]],0),MATCH('M-O-M HIGH & LOW INF'!$A46,All_India_Index_Upto_April23__1[#Headers],0)) -> 194.1 | C46: =INDEX(All_India_Index_Upto_April23__1[#All],MATCH('M-O-M HIGH & LOW INF'!C$32,All_India_Index_Upto_April23__1[[#All],[CONCAT Y&M]],0),MATCH('M-O-M HIGH & LOW INF'!A46,All_India_Index_Upto_April23__1[#Headers],0)) -> 199.9 | D46: =C46-B46 -> 5.8 | E46: =(C46-B46)/B46 -> 0.029881504
A48: Insight: December 2022 witnessed a negative inflation rate of -0.52%.
A50: Analyst Perspective: This represents "Seasonal Deflation" due to the arrival of the Fresh Winter Harvest (Rabi crops) in the markets. Increased supply in the mandis naturally cooled down the food prices, providing a much-needed dip in the overall index. | B50: Post-Shock Consolidation Phase (Feb - May 2023): | C50: Insight: From February to May 2023, the MoM inflation remained stable between 0.00% and 0.71%. | D50: Analyst Perspective: This period indicates a "Price Consolidation Phase." After the extreme volatility of mid-2022, the food basket has settled at a new, higher price level with minimal monthly fluctuations, suggesting a temporary stabilization in supply chains.

Sheet PRE VS POST COVID INF
C1: Sector | D1: Year | E1: Health | F1: Food | G1: Essential Service | H1: Health% | I1: Food% | J1: Essential Service%
C2: Rural+Sector | D2: March-2018 | E2: {=INDEX('BROADER CATEGORIES'!$X:$X,MATCH(1,('BROADER CATEGORIES'!$AS:$AS="3/2018")*('BROADER CATEGORIES'!$A:$A="Rural+Urban"),0))} -> 134.3 | F2: {=INDEX('BROADER CATEGORIES'!$AE:$AE,MATCH(1,('BROADER CATEGORIES'!$AS:$AS="3/2018")*('BROADER CATEGORIES'!$A:$A="Rural+Urban"),0))} -> 136.59286 | G2: {=INDEX('BROADER CATEGORIES'!$AT:$AT,MATCH(1,('BROADER CATEGORIES'!$AS:$AS="3/2018")*('BROADER CATEGORIES'!$A:$A="Rural+Urban"),0))} -> 139.64286 | H2: NA | I2: NA | J2: NA
C3: Rural+Sector | D3: March-2019 | E3: {=INDEX('BROADER CATEGORIES'!$X:$X,MATCH(1,('BROADER CATEGORIES'!$AS:$AS="3/2019")*('BROADER CATEGORIES'!$A:$A="Rural+Urban"),0))} -> 146.2 | F3: {=INDEX('BROADER CATEGORIES'!$AE:$AE,MATCH(1,('BROADER CATEGORIES'!$AS:$AS="3/2019")*('BROADER CATEGORIES'!$A:$A="Rural+Urban"),0))} -> 137.6 | G3: {=INDEX('BROADER CATEGORIES'!$AT:$AT,MATCH(1,('BROADER CATEGORIES'!$AS:$AS="3/2019")*('BROADER CATEGORIES'!$A:$A="Rural+Urban"),0))} -> 145.32857 | H3: =(E3-E2)*100/E2 -> 8.8607595 | I3: =(F3-F2)*100/F2 -> 0.73733201 | J3: =(G3-G2)*100/G2 -> 4.0716113
C4: Rural+Sector | D4: March-2020 | E4: {=INDEX('BROADER CATEGORIES'!$X:$X,MATCH(1,('BROADER CATEGORIES'!$AS:$AS="3/2020")*('BROADER CATEGORIES'!$A:$A="Rural+Urban"),0))} -> 152.3 | F4: {=INDEX('BROADER CATEGORIES'!$AE:$AE,MATCH(1,('BROADER CATEGORIES'!$AS:$AS="3/2020")*('BROADER CATEGORIES'!$A:$A="Rural+Urban"),0))} -> 147.61429 | G4: {=INDEX('BROADER CATEGORIES'!$AT:$AT,MATCH(1,('BROADER CATEGORIES'!$AS:$AS="3/2020")*('BROADER CATEGORIES'!$A:$A="Rural+Urban"),0))} -> 149.82857 | H4: =(E4-E3)*100/E3 -> 4.1723666 | I4: =(F4-F3)*100/F3 -> 7.2778239 | J4: =(G4-G3)*100/G3 -> 3.0964317
C5: Rural+Sector | D5: March-2021 | E5: {=INDEX('BROADER CATEGORIES'!$X:$X,MATCH(1,('BROADER CATEGORIES'!$AS:$AS="3/2021")*('BROADER CATEGORIES'!$A:$A="Rural+Urban"),0))} -> 161.7 | F5: {=INDEX('BROADER CATEGORIES'!$AE:$AE,MATCH(1,('BROADER CATEGORIES'!$AS:$AS="3/2021")*('BROADER CATEGORIES'!$A:$A="Rural+Urban"),0))} -> 159.10714 | G5: {=INDEX('BROADER CATEGORIES'!$AT:$AT,MATCH(1,('BROADER CATEGORIES'!$AS:$AS="3/2021")*('BROADER CATEGORIES'!$A:$A="Rural+Urban"),0))} -> 155.55714 | H5: =(E5-E4)*100/E4 -> 6.1720289 | I5: =(F5-F4)*100/F4 -> 7.785735 | J5: =(G5-G4)*100/G4 -> 3.8234172
C6: Rural+Sector | D6: March-2022 | E6: {=INDEX('BROADER CATEGORIES'!$X:$X,MATCH(1,('BROADER CATEGORIES'!$AS:$AS="3/2022")*('BROADER CATEGORIES'!$A:$A="Rural+Urban"),0))} -> 173 | F6: {=INDEX('BROADER CATEGORIES'!$AE:$AE,MATCH(1,('BROADER CATEGORIES'!$AS:$AS="3/2022")*('BROADER CATEGORIES'!$A:$A="Rural+Urban"),0))} -> 169.85 | G6: {=INDEX('BROADER CATEGORIES'!$AT:$AT,MATCH(1,('BROADER CATEGORIES'!$AS:$AS="3/2022")*('BROADER CATEGORIES'!$A:$A="Rural+Urban"),0))} -> 167.01429 | H6: =(E6-E5)*100/E5 -> 6.9882498 | I6: =(F6-F5)*100/F5 -> 6.7519641 | J6: =(G6-G5)*100/G5 -> 7.365231
C7: Sector | D7: Rural+Sector
C9: Row Labels | D9: Average of Food% | E9: Average of Essential Service% | F9: Average of Health%
C10: 43525 | D10: 8.8607595 | E10: 4.0716113 | F10: 0.73733201
C11: 43891 | D11: 4.1723666 | E11: 3.0964317 | F11: 7.2778239
C12: 44256 | D12: 6.1720289 | E12: 3.8234172 | F12: 7.785735
C13: 44621 | D13: 6.9882498 | E13: 7.365231 | F13: 6.7519641
C14: Grand Total | D14: 6.5483512 | E14: 4.5891728 | F14: 5.6382138
D16: Pre-Pandemic Baseline (March 2018–2019): "Agricultural Dominance"
D17: Inflation was primarily Food-driven (8.86%), while Health (0.74%) and Essential Services (4.07%) were stable. | E17: In this phase, the economy was facing "Supply-Side Shocks" in agriculture. Essential services remained low as global crude oil and logistics costs were under control. And increase msp
D21: The Pandemic Pivot (March 2019–2021): "The Healthcare Surge"
D22: As the pandemic hit, Health CPI spiked to 7.79% due to the sudden surge in medical demand (PPE, Hospital costs). | E22: Simultaneously, Essential Services dipped to 3.10% because lockdowns halted transport and communication. Food also cooled down (4.17%) due to a bumper harvest, shifting the inflation burden from the "Kitchen" to the "Hospital."
D24: The Global Recovery & War Shock (March 2021–2022): "The Service Era"
D26: Post-COVID, Essential Services hit a peak of 7.37%, surpassing the Health sector’s growth.
D28: This is the most critical turning point. The Russia-Ukraine War pushed global fuel prices up, making transport and logistics expensive. Inflation transitioned from a "Biological Crisis" (Health) to a "Geopolitical Energy Crisis" (Essential Services).

Sheet Oil Inflation analysis
A1: Year | B1: Month | C1: Crude_Oil_Price | D1: Fuel_Inflation | E1: Transport_Inflation | F1: Food_Inflation | G1: Oil_%Change | H1: Fuel_%Change | I1: Transport_%Change | J1: Food_%Change
A2: 2021 | B2: Jan | C2: 54 | D2: 4.1 | E2: 3.2 | F2: 5.5 | G2: na | H2: na | I2: na | J2: na
A3: 2021 | B3: Feb | C3: 56 | D3: 4.3 | E3: 3.5 | F3: 5.6 | G3: =(Table4[[#This Row],[Crude_Oil_Price]]-C2)/C2 -> 0.037037037 | H3: =(Table4[[#This Row],[Fuel_Inflation]]-D2)/D2 -> 0.048780488 | I3: =(Table4[[#This Row],[Transport_Inflation]]-E2)/E2 -> 0.09375 | J3: =(Table4[[#This Row],[Food_Inflation]]-F2)/F2 -> 0.018181818
A4: 2021 | B4: Mar | C4: 62 | D4: 4.8 | E4: 3.8 | F4: 5.8 | G4: =(Table4[[#This Row],[Crude_Oil_Price]]-C3)/C3 -> 0.10714286 | H4: =(Table4[[#This Row],[Fuel_Inflation]]-D3)/D3 -> 0.11627907 | I4: =(Table4[[#This Row],[Transport_Inflation]]-E3)/E3 -> 0.085714286 | J4: =(Table4[[#This Row],[Food_Inflation]]-F3)/F3 -> 0.035714286
A5: 2021 | B5: Apr | C5: 65 | D5: 5 | E5: 4.2 | F5: 6.1 | G5: =(Table4[[#This Row],[Crude_Oil_Price]]-C4)/C4 -> 0.048387097 | H5: =(Table4[[#This Row],[Fuel_Inflation]]-D4)/D4 -> 0.041666667 | I5: =(Table4[[#This Row],[Transport_Inflation]]-E4)/E4 -> 0.10526316 | J5: =(Table4[[#This Row],[Food_Inflation]]-F4)/F4 -> 0.051724138
A6: 2021 | B6: May | C6: 68 | D6: 5.4 | E6: 4.5 | F6: 6.3 | G6: =(Table4[[#This Row],[Crude_Oil_Price]]-C5)/C5 -> 0.046153846 | H6: =(Table4[[#This Row],[Fuel_Inflation]]-D5)/D5 -> 0.08 | I6: =(Table4[[#This Row],[Transport_Inflation]]-E5)/E5 -> 0.071428571 | J6: =(Table4[[#This Row],[Food_Inflation]]-F5)/F5 -> 0.032786885
A7: 2021 | B7: Jun | C7: 70 | D7: 5.8 | E7: 4.9 | F7: 6.4 | G7: =(Table4[[#This Row],[Crude_Oil_Price]]-C6)/C6 -> 0.029411765 | H7: =(Table4[[#This Row],[Fuel_Inflation]]-D6)/D6 -> 0.074074074 | I7: =(Table4[[#This Row],[Transport_Inflation]]-E6)/E6 -> 0.088888889 | J7: =(Table4[[#This Row],[Food_Inflation]]-F6)/F6 -> 0.015873016
A8: 2021 | B8: Jul | C8: 73 | D8: 6 | E8: 5.2 | F8: 6.7 | G8: =(Table4[[#This Row],[Crude_Oil_Price]]-C7)/C7 -> 0.042857143 | H8: =(Table4[[#This Row],[Fuel_Inflation]]-D7)/D7 -> 0.034482759 | I8: =(Table4[[#This Row],[Transport_Inflation]]-E7)/E7 -> 0.06122449 | J8: =(Table4[[#This Row],[Food_Inflation]]-F7)/F7 -> 0.046875
A9: 2021 | B9: Aug | C9: 71 | D9: 5.7 | E9: 4.8 | F9: 6.6 | G9: =(Table4[[#This Row],[Crude_Oil_Price]]-C8)/C8 -> -0.02739726 | H9: =(Table4[[#This Row],[Fuel_Inflation]]-D8)/D8 -> -0.05 | I9: =(Table4[[#This Row],[Transport_Inflation]]-E8)/E8 -> -0.076923077 | J9: =(Table4[[#This Row],[Food_Inflation]]-F8)/F8 -> -0.014925373
A10: 2021 | B10: Sep | C10: 72 | D10: 5.9 | E10: 5 | F10: 6.5 | G10: =(Table4[[#This Row],[Crude_Oil_Price]]-C9)/C9 -> 0.014084507 | H10: =(Table4[[#This Row],[Fuel_Inflation]]-D9)/D9 -> 0.035087719 | I10: =(Table4[[#This Row],[Transport_Inflation]]-E9)/E9 -> 0.041666667 | J10: =(Table4[[#This Row],[Food_Inflation]]-F9)/F9 -> -0.015151515
A11: 2021 | B11: Oct | C11: 75 | D11: 6.3 | E11: 5.4 | F11: 6.8 | G11: =(Table4[[#This Row],[Crude_Oil_Price]]-C10)/C10 -> 0.041666667 | H11: =(Table4[[#This Row],[Fuel_Inflation]]-D10)/D10 -> 0.06779661 | I11: =(Table4[[#This Row],[Transport_Inflation]]-E10)/E10 -> 0.08 | J11: =(Table4[[#This Row],[Food_Inflation]]-F10)/F10 -> 0.046153846
A12: 2021 | B12: Nov | C12: 77 | D12: 6.6 | E12: 5.7 | F12: 7 | G12: =(Table4[[#This Row],[Crude_Oil_Price]]-C11)/C11 -> 0.026666667 | H12: =(Table4[[#This Row],[Fuel_Inflation]]-D11)/D11 -> 0.047619048 | I12: =(Table4[[#This Row],[Transport_Inflation]]-E11)/E11 -> 0.055555556 | J12: =(Table4[[#This Row],[Food_Inflation]]-F11)/F11 -> 0.029411765
A13: 2021 | B13: Dec | C13: 79 | D13: 6.9 | E13: 6 | F13: 7.2 | G13: =(Table4[[#This Row],[Crude_Oil_Price]]-C12)/C12 -> 0.025974026 | H13: =(Table4[[#This Row],[Fuel_Inflation]]-D12)/D12 -> 0.045454545 | I13: =(Table4[[#This Row],[Transport_Inflation]]-E12)/E12 -> 0.052631579 | J13: =(Table4[[#This Row],[Food_Inflation]]-F12)/F12 -> 0.028571429
A14: 2022 | B14: Jan | C14: 81 | D14: 7.1 | E14: 6.2 | F14: 7.5 | G14: =(Table4[[#This Row],[Crude_Oil_Price]]-C13)/C13 -> 0.025316456 | H14: =(Table4[[#This Row],[Fuel_Inflation]]-D13)/D13 -> 0.028985507 | I14: =(Table4[[#This Row],[Transport_Inflation]]-E13)/E13 -> 0.033333333 | J14: =(Table4[[#This Row],[Food_Inflation]]-F13)/F13 -> 0.041666667
... A29: 2023 | B29: Apr | C29: 87 | D29: 7 | E29: 6.4 | F29: 7.6 | G29: =(Table4[[#This Row],[Crude_Oil_Price]]-C28)/C28 -> 0.048192771 | H29: =(Table4[[#This Row],[Fuel_Inflation]]-D28)/D28 -> 0.029411765 | I29: =(Table4[[#This Row],[Transport_Inflation]]-E28)/E28 -> 0.049180328 | J29: =(Table4[[#This Row],[Food_Inflation]]-F28)/F28 -> 0.04109589
A32: Inflation | B32: Correlation
A33: Fuel_Inflation | B33: =CORREL(G3:G29,H3:H29) -> 0.9297483
A34: Transport_Inflation | B34: =CORREL(G3:G29,I3:I29) -> 0.89219489
A35: Food_Inflation | B35: =CORREL(G3:G29,J3:J29) -> 0.8513728
A39: Row Labels | B39: Average of Fuel_Inflation | C39: Average of Transport_Inflation | D39: Average of Food_Inflation | E39: Average of Crude_Oil_Price
A40: 2021 | B40: 5.5666667 | C40: 4.6833333 | D40: 6.375 | E40: 68.5
A41: 2022 | B41: 7.9166667 | C41: 7.1916667 | D41: 8.025 | E41: 95.25
A42: 2023 | B42: 6.85 | C42: 6.2 | D42: 7.45 | E42: 84.25
A43: Grand Total | B43: 6.7571429 | C43: 5.975 | D43: 7.2357143 | E43: 82.214286
A65: Fuel and Transport Inflation show strong positive correlation (>0.85) with crude oil price changes, indicating oil price fluctuations significantly drive India’s inflation trends across these sectors.
A67: Insight: There is a near-perfect correlation of 0.929 (approx 0.93) between Crude Oil prices and Fuel Inflation. | B67: NSO View: This confirms that India's domestic fuel prices are almost entirely dependent on global Brent prices. Any global geopolitical shock results in an immediate increase in the cost of living at home. | C67: Insight: Transport Inflation shows a strong positive correlation of 0.892. | D67: NSO View: This represents "Supply-Side Inflation." Higher fuel costs lead to increased freight charges for trucks and logistics, which eventually "infects" all other categories of the CPI. | E67: Insight: Even Food Inflation has a high correlation of 0.851 with Oil prices. | F67: NSO View: This is a classic example of "Imported Inflation." Even if food is grown locally, the cost of tractors, irrigation, and transport to the mandi is tied to oil. This proves that global oil prices directly impact the kitchen budget of an average household.
